{
"meta":{"test_sets":[],"test_metrics":[],"learn_metrics":[{"best_value":"Min","name":"Logloss"}],"launch_mode":"Train","parameters":"","iteration_count":1000,"learn_sets":["learn"],"name":"experiment"},
"iterations":[
{"learn":[0.6770939344],"iteration":0,"passed_time":0.1567157862,"remaining_time":156.5590704},
{"learn":[0.6617937065],"iteration":1,"passed_time":0.1646285671,"remaining_time":82.14965497},
{"learn":[0.6474384151],"iteration":2,"passed_time":0.1724606249,"remaining_time":57.31441435},
{"learn":[0.6354601548],"iteration":3,"passed_time":0.178937372,"remaining_time":44.55540562},
{"learn":[0.6240480289],"iteration":4,"passed_time":0.1874172156,"remaining_time":37.2960259},
{"learn":[0.6140976728],"iteration":5,"passed_time":0.1958073202,"remaining_time":32.43874605},
{"learn":[0.6041691889],"iteration":6,"passed_time":0.2034799533,"remaining_time":28.8650848},
{"learn":[0.5942827941],"iteration":7,"passed_time":0.212274904,"remaining_time":26.3220881},
{"learn":[0.5855583431],"iteration":8,"passed_time":0.2211902139,"remaining_time":24.35550022},
{"learn":[0.5756338789],"iteration":9,"passed_time":0.2294134289,"remaining_time":22.71192946},
{"learn":[0.5652545329],"iteration":10,"passed_time":0.2375963473,"remaining_time":21.36207159},
{"learn":[0.556057525],"iteration":11,"passed_time":0.2456343906,"remaining_time":20.22389816},
{"learn":[0.5485653635],"iteration":12,"passed_time":0.2535845561,"remaining_time":19.25291976},
{"learn":[0.5415973063],"iteration":13,"passed_time":0.2617372847,"remaining_time":18.43378305},
{"learn":[0.5339946608],"iteration":14,"passed_time":0.269212478,"remaining_time":17.67828605},
{"learn":[0.5271455409],"iteration":15,"passed_time":0.2770348895,"remaining_time":17.0376457},
{"learn":[0.5209327827],"iteration":16,"passed_time":0.2847395836,"remaining_time":16.46464769},
{"learn":[0.5141938512],"iteration":17,"passed_time":0.2925165953,"remaining_time":15.95840537},
{"learn":[0.5085514835],"iteration":18,"passed_time":0.299951332,"remaining_time":15.48696088},
{"learn":[0.5037990764],"iteration":19,"passed_time":0.3077383803,"remaining_time":15.07918063},
{"learn":[0.4973461382],"iteration":20,"passed_time":0.3164491057,"remaining_time":14.75255593},
{"learn":[0.4919917737],"iteration":21,"passed_time":0.3246147328,"remaining_time":14.43060039},
{"learn":[0.4875898237],"iteration":22,"passed_time":0.3324926708,"remaining_time":14.12371041},
{"learn":[0.4825507434],"iteration":23,"passed_time":0.3404030401,"remaining_time":13.84305696},
{"learn":[0.4786994694],"iteration":24,"passed_time":0.3483547866,"remaining_time":13.58583668},
{"learn":[0.4756421253],"iteration":25,"passed_time":0.3562711199,"remaining_time":13.34646426},
{"learn":[0.4718910494],"iteration":26,"passed_time":0.3644390185,"remaining_time":13.13330241},
{"learn":[0.4686048457],"iteration":27,"passed_time":0.3724842264,"remaining_time":12.93052386},
{"learn":[0.4646046341],"iteration":28,"passed_time":0.381802281,"remaining_time":12.78379362},
{"learn":[0.4614766488],"iteration":29,"passed_time":0.3911289913,"remaining_time":12.64650405},
{"learn":[0.4588792408],"iteration":30,"passed_time":0.3996251256,"remaining_time":12.49150796},
{"learn":[0.4566060433],"iteration":31,"passed_time":0.4084844887,"remaining_time":12.35665578},
{"learn":[0.4542015833],"iteration":32,"passed_time":0.4169109873,"remaining_time":12.21675529},
{"learn":[0.4515454456],"iteration":33,"passed_time":0.424421794,"remaining_time":12.05857215},
{"learn":[0.449004521],"iteration":34,"passed_time":0.4329502395,"remaining_time":11.9370566},
{"learn":[0.4464943653],"iteration":35,"passed_time":0.4412162326,"remaining_time":11.81479023},
{"learn":[0.4443117008],"iteration":36,"passed_time":0.4513120584,"remaining_time":11.74631114},
{"learn":[0.4420991542],"iteration":37,"passed_time":0.4595831748,"remaining_time":11.6347109},
{"learn":[0.4399730322],"iteration":38,"passed_time":0.4677590887,"remaining_time":11.5260637},
{"learn":[0.4379818969],"iteration":39,"passed_time":0.4756142117,"remaining_time":11.41474108},
{"learn":[0.4360001608],"iteration":40,"passed_time":0.4841600187,"remaining_time":11.32462093},
{"learn":[0.4342687427],"iteration":41,"passed_time":0.4919171773,"remaining_time":11.22039657},
{"learn":[0.4325096001],"iteration":42,"passed_time":0.5001497284,"remaining_time":11.1312393},
{"learn":[0.4307184473],"iteration":43,"passed_time":0.50862651,"remaining_time":11.0510669},
{"learn":[0.4293627871],"iteration":44,"passed_time":0.5163131723,"remaining_time":10.95731288},
{"learn":[0.4267732412],"iteration":45,"passed_time":0.5245367075,"remaining_time":10.87843519},
{"learn":[0.424160109],"iteration":46,"passed_time":0.5323078853,"remaining_time":10.7933918},
{"learn":[0.4227545269],"iteration":47,"passed_time":0.5404949465,"remaining_time":10.71981644},
{"learn":[0.4206310651],"iteration":48,"passed_time":0.5484061164,"remaining_time":10.64355544},
{"learn":[0.4195948566],"iteration":49,"passed_time":0.5563819087,"remaining_time":10.57125627},
{"learn":[0.4178225021],"iteration":50,"passed_time":0.5642662109,"remaining_time":10.49977714},
{"learn":[0.4163865651],"iteration":51,"passed_time":0.5723406681,"remaining_time":10.43421064},
{"learn":[0.4145536483],"iteration":52,"passed_time":0.580385816,"remaining_time":10.37028996},
{"learn":[0.4135723271],"iteration":53,"passed_time":0.5895518707,"remaining_time":10.32807536},
{"learn":[0.412343348],"iteration":54,"passed_time":0.5987909133,"remaining_time":10.2883166},
{"learn":[0.4106600782],"iteration":55,"passed_time":0.6094134052,"remaining_time":10.27296883},
{"learn":[0.409563071],"iteration":56,"passed_time":0.6186731115,"remaining_time":10.23524112},
{"learn":[0.4077016613],"iteration":57,"passed_time":0.6283011298,"remaining_time":10.20447697},
{"learn":[0.4069218005],"iteration":58,"passed_time":0.6351227835,"remaining_time":10.12967016},
{"learn":[0.4047688999],"iteration":59,"passed_time":0.6456042628,"remaining_time":10.11446678},
{"learn":[0.403810781],"iteration":60,"passed_time":0.6563338151,"remaining_time":10.10323692},
{"learn":[0.4026628471],"iteration":61,"passed_time":0.6646248046,"remaining_time":10.05513011},
{"learn":[0.4018030347],"iteration":62,"passed_time":0.6765280383,"remaining_time":10.06201225},
{"learn":[0.4001637161],"iteration":63,"passed_time":0.6871610372,"remaining_time":10.04973017},
{"learn":[0.3986761726],"iteration":64,"passed_time":0.6958362092,"remaining_time":10.00933624},
{"learn":[0.3969626069],"iteration":65,"passed_time":0.7078800354,"remaining_time":10.01757505},
{"learn":[0.3951245176],"iteration":66,"passed_time":0.7159226717,"remaining_time":9.969490338},
{"learn":[0.3942725082],"iteration":67,"passed_time":0.7258430121,"remaining_time":9.94831893},
{"learn":[0.3930503568],"iteration":68,"passed_time":0.7354382188,"remaining_time":9.923086692},
{"learn":[0.3924561729],"iteration":69,"passed_time":0.7438277031,"remaining_time":9.882282341},
{"learn":[0.3916872186],"iteration":70,"passed_time":0.7517797698,"remaining_time":9.836667692},
{"learn":[0.3908334358],"iteration":71,"passed_time":0.760354856,"remaining_time":9.800129256},
{"learn":[0.3900033577],"iteration":72,"passed_time":0.7691298352,"remaining_time":9.766895304},
{"learn":[0.3891036138],"iteration":73,"passed_time":0.7771985671,"remaining_time":9.725484772},
{"learn":[0.388443636],"iteration":74,"passed_time":0.7868007384,"remaining_time":9.703875773},
{"learn":[0.3878362993],"iteration":75,"passed_time":0.7947848762,"remaining_time":9.662910863},
{"learn":[0.3871515528],"iteration":76,"passed_time":0.8049358282,"remaining_time":9.648776227},
{"learn":[0.3865246789],"iteration":77,"passed_time":0.8126450253,"remaining_time":9.60588094},
{"learn":[0.3851146929],"iteration":78,"passed_time":0.8212789202,"remaining_time":9.574656779},
{"learn":[0.3843772463],"iteration":79,"passed_time":0.8294083735,"remaining_time":9.538196296},
{"learn":[0.3838215752],"iteration":80,"passed_time":0.8378421069,"remaining_time":9.505887607},
{"learn":[0.3828489142],"iteration":81,"passed_time":0.8452269908,"remaining_time":9.462419238},
{"learn":[0.3822690359],"iteration":82,"passed_time":0.8534319437,"remaining_time":9.428880632},
{"learn":[0.3809151786],"iteration":83,"passed_time":0.8617503713,"remaining_time":9.39718262},
{"learn":[0.3794204527],"iteration":84,"passed_time":0.8686157337,"remaining_time":9.350392899},
{"learn":[0.378531172],"iteration":85,"passed_time":0.8770661881,"remaining_time":9.321377859},
{"learn":[0.377577723],"iteration":86,"passed_time":0.8849244531,"remaining_time":9.286620985},
{"learn":[0.3765112186],"iteration":87,"passed_time":0.8932833473,"remaining_time":9.257663781},
{"learn":[0.3759432813],"iteration":88,"passed_time":0.9008259949,"remaining_time":9.220814397},
{"learn":[0.3752713922],"iteration":89,"passed_time":0.9090814911,"remaining_time":9.191823965},
{"learn":[0.374751278],"iteration":90,"passed_time":0.9174752581,"remaining_time":9.164670436},
{"learn":[0.3739380178],"iteration":91,"passed_time":0.9261376518,"remaining_time":9.140575954},
{"learn":[0.3735097964],"iteration":92,"passed_time":0.9338488802,"remaining_time":9.107536928},
{"learn":[0.3730257713],"iteration":93,"passed_time":0.9420598071,"remaining_time":9.079853034},
{"learn":[0.371844379],"iteration":94,"passed_time":0.9497031809,"remaining_time":9.047172408},
{"learn":[0.3713310925],"iteration":95,"passed_time":0.9577584255,"remaining_time":9.01889184},
{"learn":[0.370852033],"iteration":96,"passed_time":0.9657159358,"remaining_time":8.990118454},
{"learn":[0.3699610676],"iteration":97,"passed_time":0.9737345062,"remaining_time":8.962331884},
{"learn":[0.3693756621],"iteration":98,"passed_time":0.9819603329,"remaining_time":8.936830908},
{"learn":[0.3689852144],"iteration":99,"passed_time":0.9909100954,"remaining_time":8.918190858},
{"learn":[0.3684018779],"iteration":100,"passed_time":0.9994098221,"remaining_time":8.895736931},
{"learn":[0.3679656465],"iteration":101,"passed_time":1.073884933,"remaining_time":9.454398725},
{"learn":[0.3675571395],"iteration":102,"passed_time":1.087934408,"remaining_time":9.474535568},
{"learn":[0.3670180794],"iteration":103,"passed_time":1.09685354,"remaining_time":9.449815113},
{"learn":[0.3666836127],"iteration":104,"passed_time":1.12076999,"remaining_time":9.553229912},
{"learn":[0.3663475498],"iteration":105,"passed_time":1.12991387,"remaining_time":9.52965094},
{"learn":[0.3660111323],"iteration":106,"passed_time":1.138338447,"remaining_time":9.500338629},
{"learn":[0.3656573353],"iteration":107,"passed_time":1.146562833,"remaining_time":9.469759693},
{"learn":[0.3652839716],"iteration":108,"passed_time":1.154556277,"remaining_time":9.437703143},
{"learn":[0.3649470812],"iteration":109,"passed_time":1.162816096,"remaining_time":9.40823932},
{"learn":[0.3645244755],"iteration":110,"passed_time":1.171156027,"remaining_time":9.379799175},
{"learn":[0.3640709533],"iteration":111,"passed_time":1.180624551,"remaining_time":9.360666082},
{"learn":[0.3636147118],"iteration":112,"passed_time":1.189104675,"remaining_time":9.333945544},
{"learn":[0.3629213643],"iteration":113,"passed_time":1.197858999,"remaining_time":9.309676078},
{"learn":[0.3625947006],"iteration":114,"passed_time":1.206326925,"remaining_time":9.283472419},
{"learn":[0.3623288947],"iteration":115,"passed_time":1.215151435,"remaining_time":9.260291968},
{"learn":[0.3620209405],"iteration":116,"passed_time":1.223882273,"remaining_time":9.236649977},
{"learn":[0.3611641133],"iteration":117,"passed_time":1.230670145,"remaining_time":9.198737863},
{"learn":[0.3608504843],"iteration":118,"passed_time":1.2391831,"remaining_time":9.174120263},
{"learn":[0.360527663],"iteration":119,"passed_time":1.246665778,"remaining_time":9.142215709},
{"learn":[0.3601300034],"iteration":120,"passed_time":1.254174414,"remaining_time":9.110903386},
{"learn":[0.3597968372],"iteration":121,"passed_time":1.261633647,"remaining_time":9.079625751},
{"learn":[0.3594020151],"iteration":122,"passed_time":1.269218912,"remaining_time":9.049634033},
{"learn":[0.3591629583],"iteration":123,"passed_time":1.277104615,"remaining_time":9.022126153},
{"learn":[0.3587642346],"iteration":124,"passed_time":1.285583969,"remaining_time":8.99908778},
{"learn":[0.3581124442],"iteration":125,"passed_time":1.294093572,"remaining_time":8.976490332},
{"learn":[0.3577986969],"iteration":126,"passed_time":1.302449694,"remaining_time":8.953059709},
{"learn":[0.3575090385],"iteration":127,"passed_time":1.311052879,"remaining_time":8.931547737},
{"learn":[0.3572188777],"iteration":128,"passed_time":1.320464315,"remaining_time":8.915693164},
{"learn":[0.3565425254],"iteration":129,"passed_time":1.329320776,"remaining_time":8.896223654},
{"learn":[0.3559051292],"iteration":130,"passed_time":1.339068933,"remaining_time":8.88283132},
{"learn":[0.3557106739],"iteration":131,"passed_time":1.347202239,"remaining_time":8.85887533},
{"learn":[0.3554403753],"iteration":132,"passed_time":1.357102276,"remaining_time":8.846674236},
{"learn":[0.3548022402],"iteration":133,"passed_time":1.366127328,"remaining_time":8.828852733},
{"learn":[0.3541091586],"iteration":134,"passed_time":1.375701001,"remaining_time":8.814676783},
{"learn":[0.3537917167],"iteration":135,"passed_time":1.383959019,"remaining_time":8.792210236},
{"learn":[0.3535873007],"iteration":136,"passed_time":1.392402148,"remaining_time":8.771117181},
{"learn":[0.3533192484],"iteration":137,"passed_time":1.401403324,"remaining_time":8.753693229},
{"learn":[0.3529981415],"iteration":138,"passed_time":1.409458759,"remaining_time":8.730532313},
{"learn":[0.352749656],"iteration":139,"passed_time":1.419053065,"remaining_time":8.717040258},
{"learn":[0.3522430198],"iteration":140,"passed_time":1.42697212,"remaining_time":8.693397527},
{"learn":[0.3518883066],"iteration":141,"passed_time":1.436991926,"remaining_time":8.682669525},
{"learn":[0.3516302446],"iteration":142,"passed_time":1.445077691,"remaining_time":8.660360706},
{"learn":[0.3513937297],"iteration":143,"passed_time":1.454607514,"remaining_time":8.646833558},
{"learn":[0.3509007784],"iteration":144,"passed_time":1.463101087,"remaining_time":8.627251238},
{"learn":[0.3506489825],"iteration":145,"passed_time":1.471934703,"remaining_time":8.60980984},
{"learn":[0.3504272165],"iteration":146,"passed_time":1.480673317,"remaining_time":8.591934281},
{"learn":[0.3501941893],"iteration":147,"passed_time":1.488902966,"remaining_time":8.57125221},
{"learn":[0.3499032305],"iteration":148,"passed_time":1.499364752,"remaining_time":8.563485935},
{"learn":[0.3493982791],"iteration":149,"passed_time":1.507233254,"remaining_time":8.540988441},
{"learn":[0.3491226012],"iteration":150,"passed_time":1.516956235,"remaining_time":8.529111546},
{"learn":[0.3489055052],"iteration":151,"passed_time":1.525028371,"remaining_time":8.508053015},
{"learn":[0.3485667231],"iteration":152,"passed_time":1.534165106,"remaining_time":8.493057809},
{"learn":[0.3481696547],"iteration":153,"passed_time":1.541586044,"remaining_time":8.468712941},
{"learn":[0.3478904299],"iteration":154,"passed_time":1.550546943,"remaining_time":8.452981724},
{"learn":[0.3476787133],"iteration":155,"passed_time":1.558668221,"remaining_time":8.432794737},
{"learn":[0.3474291342],"iteration":156,"passed_time":1.566368142,"remaining_time":8.410499007},
{"learn":[0.3472174176],"iteration":157,"passed_time":1.576095066,"remaining_time":8.399190161},
{"learn":[0.3468705665],"iteration":158,"passed_time":1.584559279,"remaining_time":8.381222351},
{"learn":[0.3467027419],"iteration":159,"passed_time":1.595615256,"remaining_time":8.376980094},
{"learn":[0.3464680004],"iteration":160,"passed_time":1.604039083,"remaining_time":8.358936587},
{"learn":[0.3462910133],"iteration":161,"passed_time":1.612154057,"remaining_time":8.339414194},
{"learn":[0.3462430127],"iteration":162,"passed_time":1.617952868,"remaining_time":8.308138347},
{"learn":[0.3459074524],"iteration":163,"passed_time":1.626440807,"remaining_time":8.290881187},
{"learn":[0.3456505727],"iteration":164,"passed_time":1.634863343,"remaining_time":8.273399342},
{"learn":[0.3452094939],"iteration":165,"passed_time":1.643385186,"remaining_time":8.256525572},
{"learn":[0.3448229774],"iteration":166,"passed_time":1.651372324,"remaining_time":8.237084706},
{"learn":[0.344646404],"iteration":167,"passed_time":1.659944009,"remaining_time":8.220675095},
{"learn":[0.3444139679],"iteration":168,"passed_time":1.667877556,"remaining_time":8.201220406},
{"learn":[0.344073176],"iteration":169,"passed_time":1.675961197,"remaining_time":8.182634081},
{"learn":[0.3438681983],"iteration":170,"passed_time":1.683720707,"remaining_time":8.162599219},
{"learn":[0.3436674178],"iteration":171,"passed_time":1.692101976,"remaining_time":8.145700211},
{"learn":[0.3429823462],"iteration":172,"passed_time":1.70027772,"remaining_time":8.127917193},
{"learn":[0.3427970535],"iteration":173,"passed_time":1.708641369,"remaining_time":8.111136613},
{"learn":[0.3418506391],"iteration":174,"passed_time":1.716672276,"remaining_time":8.092883586},
{"learn":[0.3417136721],"iteration":175,"passed_time":1.725137041,"remaining_time":8.076777965},
{"learn":[0.3414231861],"iteration":176,"passed_time":1.733474631,"remaining_time":8.060167353},
{"learn":[0.3411382865],"iteration":177,"passed_time":1.741850908,"remaining_time":8.043828352},
{"learn":[0.3406510693],"iteration":178,"passed_time":1.751721214,"remaining_time":8.034430821},
{"learn":[0.3401208762],"iteration":179,"passed_time":1.759491502,"remaining_time":8.015461285},
{"learn":[0.339980185],"iteration":180,"passed_time":1.769503542,"remaining_time":8.006759122},
{"learn":[0.3397606653],"iteration":181,"passed_time":1.777640911,"remaining_time":7.989616841},
{"learn":[0.3393176949],"iteration":182,"passed_time":1.786295208,"remaining_time":7.97488079},
{"learn":[0.339158235],"iteration":183,"passed_time":1.794617218,"remaining_time":7.958737225},
{"learn":[0.3387467724],"iteration":184,"passed_time":1.803271826,"remaining_time":7.94414345},
{"learn":[0.3385973914],"iteration":185,"passed_time":1.811733388,"remaining_time":7.928768696},
{"learn":[0.3382654666],"iteration":186,"passed_time":1.819429576,"remaining_time":7.91014035},
{"learn":[0.3380300453],"iteration":187,"passed_time":1.828085385,"remaining_time":7.895773048},
{"learn":[0.3378640828],"iteration":188,"passed_time":1.836484606,"remaining_time":7.880365162},
{"learn":[0.3377185443],"iteration":189,"passed_time":1.844868155,"remaining_time":7.864964239},
{"learn":[0.337521813],"iteration":190,"passed_time":1.852413855,"remaining_time":7.846088002},
{"learn":[0.3373207665],"iteration":191,"passed_time":1.860921436,"remaining_time":7.831377712},
{"learn":[0.3371162618],"iteration":192,"passed_time":1.868623349,"remaining_time":7.813362914},
{"learn":[0.3370163592],"iteration":193,"passed_time":1.877094208,"remaining_time":7.798649132},
{"learn":[0.3367305137],"iteration":194,"passed_time":1.885110525,"remaining_time":7.782122938},
{"learn":[0.3365311814],"iteration":195,"passed_time":1.894506531,"remaining_time":7.771343118},
{"learn":[0.3363401251],"iteration":196,"passed_time":1.902282214,"remaining_time":7.753972678},
{"learn":[0.3360789597],"iteration":197,"passed_time":1.911339465,"remaining_time":7.741890157},
{"learn":[0.3357041772],"iteration":198,"passed_time":1.918995397,"remaining_time":7.724197554},
{"learn":[0.3354901847],"iteration":199,"passed_time":1.927471368,"remaining_time":7.709885474},
{"learn":[0.3350293619],"iteration":200,"passed_time":1.934866359,"remaining_time":7.691334432},
{"learn":[0.3348537639],"iteration":201,"passed_time":1.943267631,"remaining_time":7.676869156},
{"learn":[0.3346765994],"iteration":202,"passed_time":1.95073685,"remaining_time":7.658804284},
{"learn":[0.3344777992],"iteration":203,"passed_time":1.960072828,"remaining_time":7.64812731},
{"learn":[0.3339025908],"iteration":204,"passed_time":1.968079009,"remaining_time":7.632306401},
{"learn":[0.3336935344],"iteration":205,"passed_time":1.978309323,"remaining_time":7.625133993},
{"learn":[0.3333551661],"iteration":206,"passed_time":1.987696873,"remaining_time":7.614703481},
{"learn":[0.3332360515],"iteration":207,"passed_time":1.995881523,"remaining_time":7.599702722},
{"learn":[0.3330238915],"iteration":208,"passed_time":2.00511244,"remaining_time":7.588726987},
{"learn":[0.3329198805],"iteration":209,"passed_time":2.013623494,"remaining_time":7.575059812},
{"learn":[0.3327561644],"iteration":210,"passed_time":2.022285888,"remaining_time":7.56200742},
{"learn":[0.3325644283],"iteration":211,"passed_time":2.030009875,"remaining_time":7.545508403},
{"learn":[0.3323956875],"iteration":212,"passed_time":2.039721998,"remaining_time":7.536437619},
{"learn":[0.3321920991],"iteration":213,"passed_time":2.047185804,"remaining_time":7.519103001},
{"learn":[0.3317545376],"iteration":214,"passed_time":2.056056205,"remaining_time":7.50699591},
{"learn":[0.3316727534],"iteration":215,"passed_time":2.063615073,"remaining_time":7.490158413},
{"learn":[0.3314953525],"iteration":216,"passed_time":2.07214531,"remaining_time":7.476911417},
{"learn":[0.3313484838],"iteration":217,"passed_time":2.079799912,"remaining_time":7.460566658},
{"learn":[0.3312102459],"iteration":218,"passed_time":2.087792956,"remaining_time":7.445508213},
{"learn":[0.3308634539],"iteration":219,"passed_time":2.09574081,"remaining_time":7.430353781},
{"learn":[0.3306741119],"iteration":220,"passed_time":2.104222665,"remaining_time":7.41714686},
{"learn":[0.3306278256],"iteration":221,"passed_time":2.109873899,"remaining_time":7.394062584},
{"learn":[0.3303434284],"iteration":222,"passed_time":2.118926449,"remaining_time":7.38298588},
{"learn":[0.3301440371],"iteration":223,"passed_time":2.126081292,"remaining_time":7.365353048},
{"learn":[0.3300055331],"iteration":224,"passed_time":2.134875803,"remaining_time":7.353461098},
{"learn":[0.3298207133],"iteration":225,"passed_time":2.142110418,"remaining_time":7.336254263},
{"learn":[0.3296120115],"iteration":226,"passed_time":2.150881293,"remaining_time":7.324366693},
{"learn":[0.3293902455],"iteration":227,"passed_time":2.158343768,"remaining_time":7.308076266},
{"learn":[0.3292130514],"iteration":228,"passed_time":2.167577827,"remaining_time":7.297827531},
{"learn":[0.3290413845],"iteration":229,"passed_time":2.175882155,"remaining_time":7.284475042},
{"learn":[0.3288761314],"iteration":230,"passed_time":2.184830107,"remaining_time":7.273308883},
{"learn":[0.328722376],"iteration":231,"passed_time":2.193950761,"remaining_time":7.262733555},
{"learn":[0.3285721379],"iteration":232,"passed_time":2.201801532,"remaining_time":7.24799045},
{"learn":[0.3283543621],"iteration":233,"passed_time":2.210383212,"remaining_time":7.235698891},
{"learn":[0.3280288512],"iteration":234,"passed_time":2.218180857,"remaining_time":7.220886621},
{"learn":[0.327899362],"iteration":235,"passed_time":2.227904539,"remaining_time":7.21236893},
{"learn":[0.3277884643],"iteration":236,"passed_time":2.235770229,"remaining_time":7.197859428},
{"learn":[0.3276597141],"iteration":237,"passed_time":2.244513996,"remaining_time":7.186217079},
{"learn":[0.3275587474],"iteration":238,"passed_time":2.252226735,"remaining_time":7.17131609},
{"learn":[0.3274530517],"iteration":239,"passed_time":2.261603218,"remaining_time":7.161743524},
{"learn":[0.3273143113],"iteration":240,"passed_time":2.268932976,"remaining_time":7.145726675},
{"learn":[0.3269907215],"iteration":241,"passed_time":2.278291487,"remaining_time":7.136136145},
{"learn":[0.3268269758],"iteration":242,"passed_time":2.285652425,"remaining_time":7.120324633},
{"learn":[0.3266447571],"iteration":243,"passed_time":2.294661557,"remaining_time":7.109689085},
{"learn":[0.3265395933],"iteration":244,"passed_time":2.302202053,"remaining_time":7.09454102},
{"learn":[0.3263626357],"iteration":245,"passed_time":2.311036349,"remaining_time":7.083420356},
{"learn":[0.3261941018],"iteration":246,"passed_time":2.318606175,"remaining_time":7.068463359},
{"learn":[0.3259670452],"iteration":247,"passed_time":2.32734641,"remaining_time":7.05711492},
{"learn":[0.3258446793],"iteration":248,"passed_time":2.334959874,"remaining_time":7.042389017},
{"learn":[0.3256603029],"iteration":249,"passed_time":2.343637908,"remaining_time":7.030913723},
{"learn":[0.3255206166],"iteration":250,"passed_time":2.351518408,"remaining_time":7.017080826},
{"learn":[0.3252669291],"iteration":251,"passed_time":2.360919708,"remaining_time":7.007809293},
{"learn":[0.3250901783],"iteration":252,"passed_time":2.370602871,"remaining_time":6.999368952},
{"learn":[0.3247936923],"iteration":253,"passed_time":2.378776924,"remaining_time":6.986486556},
{"learn":[0.3246311289],"iteration":254,"passed_time":2.387911388,"remaining_time":6.976446996},
{"learn":[0.3245128715],"iteration":255,"passed_time":2.396284541,"remaining_time":6.964201948},
{"learn":[0.3243790079],"iteration":256,"passed_time":2.406234571,"remaining_time":6.956545862},
{"learn":[0.3241998926],"iteration":257,"passed_time":2.414582638,"remaining_time":6.944264797},
{"learn":[0.3240629552],"iteration":258,"passed_time":2.424498956,"remaining_time":6.936500875},
{"learn":[0.3236684582],"iteration":259,"passed_time":2.433353416,"remaining_time":6.925698184},
{"learn":[0.3234774019],"iteration":260,"passed_time":2.441351683,"remaining_time":6.912486183},
{"learn":[0.3232675474],"iteration":261,"passed_time":2.449728719,"remaining_time":6.900380896},
{"learn":[0.3230773778],"iteration":262,"passed_time":2.457450324,"remaining_time":6.886467259},
{"learn":[0.3229387851],"iteration":263,"passed_time":2.466004347,"remaining_time":6.874921209},
{"learn":[0.3227894928],"iteration":264,"passed_time":2.473391012,"remaining_time":6.860159977},
{"learn":[0.3225452931],"iteration":265,"passed_time":2.482336452,"remaining_time":6.849755472},
{"learn":[0.3224290751],"iteration":266,"passed_time":2.490137539,"remaining_time":6.836220285},
{"learn":[0.3223963851],"iteration":267,"passed_time":2.496791523,"remaining_time":6.819594756},
{"learn":[0.3220794752],"iteration":268,"passed_time":2.504875156,"remaining_time":6.806928397},
{"learn":[0.3218873844],"iteration":269,"passed_time":2.5144184,"remaining_time":6.798242341},
{"learn":[0.3217337177],"iteration":270,"passed_time":2.52217991,"remaining_time":6.784757027},
{"learn":[0.3215734006],"iteration":271,"passed_time":2.531114212,"remaining_time":6.774452745},
{"learn":[0.3213877237],"iteration":272,"passed_time":2.539273056,"remaining_time":6.762093451},
{"learn":[0.3212633479],"iteration":273,"passed_time":2.548664879,"remaining_time":6.753031761},
{"learn":[0.3209428912],"iteration":274,"passed_time":2.556142164,"remaining_time":6.738920251},
{"learn":[0.3207744164],"iteration":275,"passed_time":2.565480202,"remaining_time":6.729737921},
{"learn":[0.3206253606],"iteration":276,"passed_time":2.573387519,"remaining_time":6.716820131},
{"learn":[0.320448935],"iteration":277,"passed_time":2.582655561,"remaining_time":6.707472356},
{"learn":[0.3202618689],"iteration":278,"passed_time":2.591938202,"remaining_time":6.698162881},
{"learn":[0.3201160643],"iteration":279,"passed_time":2.599995178,"remaining_time":6.685701886},
{"learn":[0.3198557856],"iteration":280,"passed_time":2.609072304,"remaining_time":6.675882515},
{"learn":[0.3196991927],"iteration":281,"passed_time":2.616785454,"remaining_time":6.662595588},
{"learn":[0.319585694],"iteration":282,"passed_time":2.625393822,"remaining_time":6.651616149},
{"learn":[0.3195001561],"iteration":283,"passed_time":2.633172815,"remaining_time":6.638562449},
{"learn":[0.3192943804],"iteration":284,"passed_time":2.641072787,"remaining_time":6.625849273},
{"learn":[0.3191301618],"iteration":285,"passed_time":2.649153799,"remaining_time":6.613621722},
{"learn":[0.3188664545],"iteration":286,"passed_time":2.657628729,"remaining_time":6.602401686},
{"learn":[0.3186915659],"iteration":287,"passed_time":2.66593622,"remaining_time":6.590786765},
{"learn":[0.3183071478],"iteration":288,"passed_time":2.67482239,"remaining_time":6.580618406},
{"learn":[0.3181514121],"iteration":289,"passed_time":2.682399541,"remaining_time":6.567254048},
{"learn":[0.3180438838],"iteration":290,"passed_time":2.691173217,"remaining_time":6.556844712},
{"learn":[0.3178998231],"iteration":291,"passed_time":2.698633631,"remaining_time":6.543262365},
{"learn":[0.3177549348],"iteration":292,"passed_time":2.70719806,"remaining_time":6.532385763},
{"learn":[0.3176137116],"iteration":293,"passed_time":2.714859806,"remaining_time":6.519357221},
{"learn":[0.3175194248],"iteration":294,"passed_time":2.722668549,"remaining_time":6.506716362},
{"learn":[0.3173264769],"iteration":295,"passed_time":2.730229999,"remaining_time":6.493519997},
{"learn":[0.3172018056],"iteration":296,"passed_time":2.738442677,"remaining_time":6.481903036},
{"learn":[0.316928906],"iteration":297,"passed_time":2.746079216,"remaining_time":6.46895171},
{"learn":[0.3167252584],"iteration":298,"passed_time":2.754171025,"remaining_time":6.457103305},
{"learn":[0.3166339569],"iteration":299,"passed_time":2.761759232,"remaining_time":6.444104875},
{"learn":[0.3164764774],"iteration":300,"passed_time":2.769703584,"remaining_time":6.431969452},
{"learn":[0.3163541706],"iteration":301,"passed_time":2.77766971,"remaining_time":6.419912111},
{"learn":[0.3160714581],"iteration":302,"passed_time":2.786211704,"remaining_time":6.409206462},
{"learn":[0.3157971398],"iteration":303,"passed_time":2.794089262,"remaining_time":6.396993837},
{"learn":[0.3156188817],"iteration":304,"passed_time":2.802696059,"remaining_time":6.386471348},
{"learn":[0.3153267997],"iteration":305,"passed_time":2.810711708,"remaining_time":6.37462067},
{"learn":[0.3151290044],"iteration":306,"passed_time":2.819574693,"remaining_time":6.364707695},
{"learn":[0.3150171017],"iteration":307,"passed_time":2.82763408,"remaining_time":6.352996051},
{"learn":[0.3148918096],"iteration":308,"passed_time":2.836279433,"remaining_time":6.342618408},
{"learn":[0.3147679364],"iteration":309,"passed_time":2.84404935,"remaining_time":6.330303391},
{"learn":[0.3146343979],"iteration":310,"passed_time":2.85305637,"remaining_time":6.320758324},
{"learn":[0.3144694996],"iteration":311,"passed_time":2.861461775,"remaining_time":6.309890067},
{"learn":[0.3143391533],"iteration":312,"passed_time":2.869159014,"remaining_time":6.297483203},
{"learn":[0.3142440389],"iteration":313,"passed_time":2.877509723,"remaining_time":6.28653398},
{"learn":[0.3140808549],"iteration":314,"passed_time":2.885258186,"remaining_time":6.27429161},
{"learn":[0.3139559471],"iteration":315,"passed_time":2.893740461,"remaining_time":6.263666061},
{"learn":[0.3138101425],"iteration":316,"passed_time":2.901840325,"remaining_time":6.2522301},
{"learn":[0.3137424571],"iteration":317,"passed_time":2.909940369,"remaining_time":6.240815508},
{"learn":[0.3135340804],"iteration":318,"passed_time":2.917396099,"remaining_time":6.228046218},
{"learn":[0.3133929458],"iteration":319,"passed_time":2.925377205,"remaining_time":6.21642656},
{"learn":[0.3131752587],"iteration":320,"passed_time":2.932835287,"remaining_time":6.203723239},
{"learn":[0.3129360541],"iteration":321,"passed_time":2.941013232,"remaining_time":6.192568234},
{"learn":[0.3127954515],"iteration":322,"passed_time":2.948656076,"remaining_time":6.180310103},
{"learn":[0.3126767507],"iteration":323,"passed_time":2.956518223,"remaining_time":6.168538021},
{"learn":[0.3125501582],"iteration":324,"passed_time":2.963995648,"remaining_time":6.155990961},
{"learn":[0.3123888067],"iteration":325,"passed_time":2.972836269,"remaining_time":6.14629339},
{"learn":[0.3121623411],"iteration":326,"passed_time":2.98046024,"remaining_time":6.134097069},
{"learn":[0.3120379062],"iteration":327,"passed_time":2.989200325,"remaining_time":6.124215299},
{"learn":[0.3118523475],"iteration":328,"passed_time":2.996762455,"remaining_time":6.111938016},
{"learn":[0.3117702678],"iteration":329,"passed_time":3.005894307,"remaining_time":6.102876321},
{"learn":[0.3116166602],"iteration":330,"passed_time":3.013658581,"remaining_time":6.091050122},
{"learn":[0.311507595],"iteration":331,"passed_time":3.0222694,"remaining_time":6.080951685},
{"learn":[0.3113271792],"iteration":332,"passed_time":3.030157315,"remaining_time":6.069414201},
{"learn":[0.311170675],"iteration":333,"passed_time":3.040380294,"remaining_time":6.062554718},
{"learn":[0.310975865],"iteration":334,"passed_time":3.048423681,"remaining_time":6.051348501},
{"learn":[0.3108360605],"iteration":335,"passed_time":3.057205823,"remaining_time":6.041621032},
{"learn":[0.3106852608],"iteration":336,"passed_time":3.064520031,"remaining_time":6.029011218},
{"learn":[0.3105305004],"iteration":337,"passed_time":3.07291757,"remaining_time":6.018554531},
{"learn":[0.3104329624],"iteration":338,"passed_time":3.080282891,"remaining_time":6.006097319},
{"learn":[0.3102816898],"iteration":339,"passed_time":3.089138142,"remaining_time":5.996562275},
{"learn":[0.3101271364],"iteration":340,"passed_time":3.096385285,"remaining_time":5.983923469},
{"learn":[0.3098609758],"iteration":341,"passed_time":3.104678116,"remaining_time":5.973328071},
{"learn":[0.3097719206],"iteration":342,"passed_time":3.111660795,"remaining_time":5.960236567},
{"learn":[0.3096462739],"iteration":343,"passed_time":3.11971648,"remaining_time":5.949226776},
{"learn":[0.3095138291],"iteration":344,"passed_time":3.127402752,"remaining_time":5.937532762},
{"learn":[0.3093436696],"iteration":345,"passed_time":3.135127089,"remaining_time":5.925933862},
{"learn":[0.3091727712],"iteration":346,"passed_time":3.14284179,"remaining_time":5.914339161},
{"learn":[0.3090149369],"iteration":347,"passed_time":3.151069398,"remaining_time":5.903727722},
{"learn":[0.3089244926],"iteration":348,"passed_time":3.158249237,"remaining_time":5.891175511},
{"learn":[0.3087316629],"iteration":349,"passed_time":3.165698974,"remaining_time":5.879155237},
{"learn":[0.3085757794],"iteration":350,"passed_time":3.173203736,"remaining_time":5.867262749},
{"learn":[0.3083721318],"iteration":351,"passed_time":3.181943441,"remaining_time":5.857668607},
{"learn":[0.3082392436],"iteration":352,"passed_time":3.189881829,"remaining_time":5.846610604},
{"learn":[0.3081109368],"iteration":353,"passed_time":3.198727983,"remaining_time":5.837226771},
{"learn":[0.3079916744],"iteration":354,"passed_time":3.206492436,"remaining_time":5.825880624},
{"learn":[0.3077448736],"iteration":355,"passed_time":3.215431362,"remaining_time":5.816679205},
{"learn":[0.3075663495],"iteration":356,"passed_time":3.223693933,"remaining_time":5.806261061},
{"learn":[0.3074730086],"iteration":357,"passed_time":3.233068354,"remaining_time":5.797848836},
{"learn":[0.3072990066],"iteration":358,"passed_time":3.240829135,"remaining_time":5.786550071},
{"learn":[0.307133724],"iteration":359,"passed_time":3.249829651,"remaining_time":5.777474935},
{"learn":[0.3069380273],"iteration":360,"passed_time":3.257360301,"remaining_time":5.765798427},
{"learn":[0.3067895922],"iteration":361,"passed_time":3.265980307,"remaining_time":5.756064739},
{"learn":[0.3066076394],"iteration":362,"passed_time":3.273752015,"remaining_time":5.744848577},
{"learn":[0.3063723659],"iteration":363,"passed_time":3.282419322,"remaining_time":5.735216177},
{"learn":[0.3061753391],"iteration":364,"passed_time":3.289897697,"remaining_time":5.723520651},
{"learn":[0.3060824119],"iteration":365,"passed_time":3.297914947,"remaining_time":5.712781629},
{"learn":[0.3058785279],"iteration":366,"passed_time":3.305442164,"remaining_time":5.701212234},
{"learn":[0.3057425658],"iteration":367,"passed_time":3.313829257,"remaining_time":5.69114155},
{"learn":[0.3055732044],"iteration":368,"passed_time":3.321229841,"remaining_time":5.679393034},
{"learn":[0.3053707686],"iteration":369,"passed_time":3.329463173,"remaining_time":5.669085942},
{"learn":[0.3052152103],"iteration":370,"passed_time":3.33718617,"remaining_time":5.657924801},
{"learn":[0.3050126267],"iteration":371,"passed_time":3.345695053,"remaining_time":5.648108853},
{"learn":[0.3048960245],"iteration":372,"passed_time":3.353467942,"remaining_time":5.637062733},
{"learn":[0.3047621609],"iteration":373,"passed_time":3.362089387,"remaining_time":5.627454429},
{"learn":[0.3046189278],"iteration":374,"passed_time":3.370460079,"remaining_time":5.617433465},
{"learn":[0.3044571329],"iteration":375,"passed_time":3.379679419,"remaining_time":5.608829674},
{"learn":[0.3043517919],"iteration":376,"passed_time":3.389233889,"remaining_time":5.600776426},
{"learn":[0.3042207953],"iteration":377,"passed_time":3.397870816,"remaining_time":5.591205416},
{"learn":[0.3041170799],"iteration":378,"passed_time":3.406946761,"remaining_time":5.582358677},
{"learn":[0.3039989407],"iteration":379,"passed_time":3.41482647,"remaining_time":5.571558978},
{"learn":[0.3038178155],"iteration":380,"passed_time":3.423993906,"remaining_time":5.562866739},
{"learn":[0.3036629961],"iteration":381,"passed_time":3.431834639,"remaining_time":5.552025673},
{"learn":[0.3035438519],"iteration":382,"passed_time":3.440878774,"remaining_time":5.543138912},
{"learn":[0.3034127076],"iteration":383,"passed_time":3.448472495,"remaining_time":5.531924627},
{"learn":[0.3032949526],"iteration":384,"passed_time":3.458014777,"remaining_time":5.523841787},
{"learn":[0.3031336306],"iteration":385,"passed_time":3.465440958,"remaining_time":5.512385358},
{"learn":[0.302973757],"iteration":386,"passed_time":3.474144048,"remaining_time":5.502972356},
{"learn":[0.3028429082],"iteration":387,"passed_time":3.481383927,"remaining_time":5.49125506},
{"learn":[0.3027079215],"iteration":388,"passed_time":3.490172023,"remaining_time":5.481992561},
{"learn":[0.3025030917],"iteration":389,"passed_time":3.497401965,"remaining_time":5.470295382},
{"learn":[0.3023303902],"iteration":390,"passed_time":3.505339302,"remaining_time":5.459722852},
{"learn":[0.3021887237],"iteration":391,"passed_time":3.512901583,"remaining_time":5.448582047},
{"learn":[0.3020665056],"iteration":392,"passed_time":3.520834037,"remaining_time":5.438031197},
{"learn":[0.3018932426],"iteration":393,"passed_time":3.529380624,"remaining_time":5.428438219},
{"learn":[0.3017266594],"iteration":394,"passed_time":3.537418449,"remaining_time":5.418071295},
{"learn":[0.3015618497],"iteration":395,"passed_time":3.544684783,"remaining_time":5.406539417},
{"learn":[0.3014022421],"iteration":396,"passed_time":3.552397995,"remaining_time":5.395707785},
{"learn":[0.3012507626],"iteration":397,"passed_time":3.559713281,"remaining_time":5.384289938},
{"learn":[0.3011323869],"iteration":398,"passed_time":3.567885573,"remaining_time":5.374183532},
{"learn":[0.3010043461],"iteration":399,"passed_time":3.57556465,"remaining_time":5.363346975},
{"learn":[0.3008526892],"iteration":400,"passed_time":3.584150343,"remaining_time":5.353880438},
{"learn":[0.300708599],"iteration":401,"passed_time":3.591932288,"remaining_time":5.343222658},
{"learn":[0.3005998884],"iteration":402,"passed_time":3.600373486,"remaining_time":5.33355576},
{"learn":[0.3004535814],"iteration":403,"passed_time":3.608485588,"remaining_time":5.323409432},
{"learn":[0.3002925254],"iteration":404,"passed_time":3.617787222,"remaining_time":5.315020734},
{"learn":[0.3001324153],"iteration":405,"passed_time":3.627161974,"remaining_time":5.306734514},
{"learn":[0.300036562],"iteration":406,"passed_time":3.635300153,"remaining_time":5.296641255},
{"learn":[0.2999043536],"iteration":407,"passed_time":3.644711579,"remaining_time":5.288405036},
{"learn":[0.2997746872],"iteration":408,"passed_time":3.65297376,"remaining_time":5.278502425},
{"learn":[0.2995995325],"iteration":409,"passed_time":3.661753891,"remaining_time":5.26935316},
{"learn":[0.2994502107],"iteration":410,"passed_time":3.669554778,"remaining_time":5.258802346},
{"learn":[0.2992962484],"iteration":411,"passed_time":3.679682895,"remaining_time":5.251586268},
{"learn":[0.2991164533],"iteration":412,"passed_time":3.687956383,"remaining_time":5.241720089},
{"learn":[0.299000856],"iteration":413,"passed_time":3.697470216,"remaining_time":5.233617263},
{"learn":[0.2988620269],"iteration":414,"passed_time":3.706679299,"remaining_time":5.225078048},
{"learn":[0.2987275131],"iteration":415,"passed_time":3.714802598,"remaining_time":5.21501134},
{"learn":[0.2985679645],"iteration":416,"passed_time":3.724151143,"remaining_time":5.206666946},
{"learn":[0.2984356379],"iteration":417,"passed_time":3.733677024,"remaining_time":5.198564661},
{"learn":[0.2982511137],"iteration":418,"passed_time":3.742740962,"remaining_time":5.189815033},
{"learn":[0.2981056047],"iteration":419,"passed_time":3.751397542,"remaining_time":5.180501367},
{"learn":[0.2979449625],"iteration":420,"passed_time":3.760367187,"remaining_time":5.171621381},
{"learn":[0.2978133453],"iteration":421,"passed_time":3.768798519,"remaining_time":5.162003659},
{"learn":[0.2977132359],"iteration":422,"passed_time":3.77754787,"remaining_time":5.152825345},
{"learn":[0.2975591553],"iteration":423,"passed_time":3.786841738,"remaining_time":5.144388777},
{"learn":[0.2973386307],"iteration":424,"passed_time":3.795095173,"remaining_time":5.134540528},
{"learn":[0.2971874764],"iteration":425,"passed_time":3.804505228,"remaining_time":5.126258218},
{"learn":[0.2970273662],"iteration":426,"passed_time":3.812278547,"remaining_time":5.115774257},
{"learn":[0.2969005963],"iteration":427,"passed_time":3.821398192,"remaining_time":5.107102256},
{"learn":[0.296783462],"iteration":428,"passed_time":3.8293373,"remaining_time":5.096856872},
{"learn":[0.2966404358],"iteration":429,"passed_time":3.838144248,"remaining_time":5.087772608},
{"learn":[0.2965210257],"iteration":430,"passed_time":3.84627174,"remaining_time":5.077792623},
{"learn":[0.2963557726],"iteration":431,"passed_time":3.854665998,"remaining_time":5.06817196},
{"learn":[0.2962225889],"iteration":432,"passed_time":3.862410988,"remaining_time":5.057706768},
{"learn":[0.29606106],"iteration":433,"passed_time":3.871688556,"remaining_time":5.049252818},
{"learn":[0.2959628126],"iteration":434,"passed_time":3.879265066,"remaining_time":5.038585661},
{"learn":[0.295857708],"iteration":435,"passed_time":3.88789686,"remaining_time":5.029297773},
{"learn":[0.2957374702],"iteration":436,"passed_time":3.895418464,"remaining_time":5.018582597},
{"learn":[0.2955653008],"iteration":437,"passed_time":3.904319864,"remaining_time":5.009652429},
{"learn":[0.2954528365],"iteration":438,"passed_time":3.912505765,"remaining_time":4.99980805},
{"learn":[0.2953028644],"iteration":439,"passed_time":3.92047057,"remaining_time":4.989689816},
{"learn":[0.2951494933],"iteration":440,"passed_time":3.928791319,"remaining_time":4.980032534},
{"learn":[0.2950425266],"iteration":441,"passed_time":3.936721421,"remaining_time":4.969888129},
{"learn":[0.2949455797],"iteration":442,"passed_time":3.944834484,"remaining_time":4.959983764},
{"learn":[0.2948287114],"iteration":443,"passed_time":3.952698873,"remaining_time":4.949776066},
{"learn":[0.294743942],"iteration":444,"passed_time":3.960387667,"remaining_time":4.939359899},
{"learn":[0.2946244727],"iteration":445,"passed_time":3.968332208,"remaining_time":4.92927364},
{"learn":[0.2944961659],"iteration":446,"passed_time":3.976074607,"remaining_time":4.918946886},
{"learn":[0.2943185284],"iteration":447,"passed_time":3.984433932,"remaining_time":4.909391809},
{"learn":[0.2942022217],"iteration":448,"passed_time":3.993154033,"remaining_time":4.900284794},
{"learn":[0.2940236976],"iteration":449,"passed_time":4.000998659,"remaining_time":4.890109473},
{"learn":[0.2939080412],"iteration":450,"passed_time":4.009743587,"remaining_time":4.88104042},
{"learn":[0.2937993602],"iteration":451,"passed_time":4.017836226,"remaining_time":4.871181974},
{"learn":[0.2937007876],"iteration":452,"passed_time":4.02748695,"remaining_time":4.863212718},
{"learn":[0.2935757912],"iteration":453,"passed_time":4.035448563,"remaining_time":4.853204659},
{"learn":[0.2934219176],"iteration":454,"passed_time":4.045229872,"remaining_time":4.845385231},
{"learn":[0.2933213056],"iteration":455,"passed_time":4.053579059,"remaining_time":4.835848702},
{"learn":[0.2932002402],"iteration":456,"passed_time":4.06280019,"remaining_time":4.827353399},
{"learn":[0.2930877168],"iteration":457,"passed_time":4.070698282,"remaining_time":4.817289233},
{"learn":[0.2929970656],"iteration":458,"passed_time":4.079638378,"remaining_time":4.808462663},
{"learn":[0.2928959807],"iteration":459,"passed_time":4.087856399,"remaining_time":4.798787947},
{"learn":[0.2927417524],"iteration":460,"passed_time":4.096983348,"remaining_time":4.790182266},
{"learn":[0.292569317],"iteration":461,"passed_time":4.106221941,"remaining_time":4.781704338},
{"learn":[0.2924798481],"iteration":462,"passed_time":4.11398084,"remaining_time":4.771506936},
{"learn":[0.292341551],"iteration":463,"passed_time":4.123026416,"remaining_time":4.762806377},
{"learn":[0.292214722],"iteration":464,"passed_time":4.131053572,"remaining_time":4.752932604},
{"learn":[0.2921163859],"iteration":465,"passed_time":4.139715805,"remaining_time":4.743794507},
{"learn":[0.2919304134],"iteration":466,"passed_time":4.148086337,"remaining_time":4.73432552},
{"learn":[0.2917847566],"iteration":467,"passed_time":4.157353128,"remaining_time":4.725880052},
{"learn":[0.2916766077],"iteration":468,"passed_time":4.165182524,"remaining_time":4.715803668},
{"learn":[0.2915428032],"iteration":469,"passed_time":4.174648796,"remaining_time":4.707582685},
{"learn":[0.2914090284],"iteration":470,"passed_time":4.182933462,"remaining_time":4.698029302},
{"learn":[0.2912880812],"iteration":471,"passed_time":4.191460626,"remaining_time":4.688752565},
{"learn":[0.2911761194],"iteration":472,"passed_time":4.199219936,"remaining_time":4.678623481},
{"learn":[0.291029901],"iteration":473,"passed_time":4.206895491,"remaining_time":4.668411452},
{"learn":[0.2909335157],"iteration":474,"passed_time":4.214944672,"remaining_time":4.658623058},
{"learn":[0.2908482734],"iteration":475,"passed_time":4.223292529,"remaining_time":4.649170767},
{"learn":[0.2907526566],"iteration":476,"passed_time":4.231645869,"remaining_time":4.639729119},
{"learn":[0.2906153053],"iteration":477,"passed_time":4.239587999,"remaining_time":4.629842962},
{"learn":[0.2904770378],"iteration":478,"passed_time":4.247502541,"remaining_time":4.619934915},
{"learn":[0.2903291347],"iteration":479,"passed_time":4.255233043,"remaining_time":4.609835796},
{"learn":[0.2902105521],"iteration":480,"passed_time":4.262612853,"remaining_time":4.599368131},
{"learn":[0.2901128367],"iteration":481,"passed_time":4.270560357,"remaining_time":4.589523371},
{"learn":[0.2900173677],"iteration":482,"passed_time":4.278153629,"remaining_time":4.579307301},
{"learn":[0.2898511984],"iteration":483,"passed_time":4.286952463,"remaining_time":4.570387336},
{"learn":[0.2897309015],"iteration":484,"passed_time":4.29524063,"remaining_time":4.560925618},
{"learn":[0.2895982498],"iteration":485,"passed_time":4.302909191,"remaining_time":4.550813424},
{"learn":[0.2894962191],"iteration":486,"passed_time":4.311148376,"remaining_time":4.541312355},
{"learn":[0.2893577151],"iteration":487,"passed_time":4.319182377,"remaining_time":4.531601182},
{"learn":[0.2892256545],"iteration":488,"passed_time":4.327215777,"remaining_time":4.521896241},
{"learn":[0.2891155843],"iteration":489,"passed_time":4.334990417,"remaining_time":4.511928801},
{"learn":[0.2889956717],"iteration":490,"passed_time":4.343175327,"remaining_time":4.502395604},
{"learn":[0.28892373],"iteration":491,"passed_time":4.350989883,"remaining_time":4.492485489},
{"learn":[0.2888249801],"iteration":492,"passed_time":4.358918765,"remaining_time":4.482701448},
{"learn":[0.2887394422],"iteration":493,"passed_time":4.366935014,"remaining_time":4.473014407},
{"learn":[0.2886103965],"iteration":494,"passed_time":4.375173268,"remaining_time":4.463560607},
{"learn":[0.2885298242],"iteration":495,"passed_time":4.384236886,"remaining_time":4.454950384},
{"learn":[0.2884049164],"iteration":496,"passed_time":4.393498103,"remaining_time":4.446538321},
{"learn":[0.288255565],"iteration":497,"passed_time":4.401835843,"remaining_time":4.437191954},
{"learn":[0.2881017209],"iteration":498,"passed_time":4.41164442,"remaining_time":4.429326362},
{"learn":[0.2879732072],"iteration":499,"passed_time":4.423719188,"remaining_time":4.423719188},
{"learn":[0.2878818761],"iteration":500,"passed_time":4.433579909,"remaining_time":4.415880988},
{"learn":[0.2877737567],"iteration":501,"passed_time":4.444500187,"remaining_time":4.409085843},
{"learn":[0.2876752138],"iteration":502,"passed_time":4.452485546,"remaining_time":4.399374386},
{"learn":[0.2875628381],"iteration":503,"passed_time":4.462134688,"remaining_time":4.391307153},
{"learn":[0.2874553099],"iteration":504,"passed_time":4.470689301,"remaining_time":4.3821608},
{"learn":[0.2873700084],"iteration":505,"passed_time":4.47934481,"remaining_time":4.373115289},
{"learn":[0.2872289034],"iteration":506,"passed_time":4.489823587,"remaining_time":4.365844238},
{"learn":[0.2871112666],"iteration":507,"passed_time":4.498504883,"remaining_time":4.35681969},
{"learn":[0.2870308126],"iteration":508,"passed_time":4.50755255,"remaining_time":4.348149906},
{"learn":[0.2869095994],"iteration":509,"passed_time":4.516019095,"remaining_time":4.338920307},
{"learn":[0.286804081],"iteration":510,"passed_time":4.526793327,"remaining_time":4.331902029},
{"learn":[0.2866745032],"iteration":511,"passed_time":4.537620183,"remaining_time":4.324919237},
{"learn":[0.2865785317],"iteration":512,"passed_time":4.546286619,"remaining_time":4.315870533},
{"learn":[0.2864979003],"iteration":513,"passed_time":4.555516366,"remaining_time":4.307355941},
{"learn":[0.2864165595],"iteration":514,"passed_time":4.563813519,"remaining_time":4.297960305},
{"learn":[0.2862590799],"iteration":515,"passed_time":4.573469636,"remaining_time":4.289843612},
{"learn":[0.28612764],"iteration":516,"passed_time":4.582805793,"remaining_time":4.281422046},
{"learn":[0.2859202387],"iteration":517,"passed_time":4.591933772,"remaining_time":4.27280324},
{"learn":[0.2857956856],"iteration":518,"passed_time":4.600655315,"remaining_time":4.263805793},
{"learn":[0.285679172],"iteration":519,"passed_time":4.609059258,"remaining_time":4.254516239},
{"learn":[0.285526924],"iteration":520,"passed_time":4.618182195,"remaining_time":4.245891116},
{"learn":[0.2854448443],"iteration":521,"passed_time":4.625884267,"remaining_time":4.235962988},
{"learn":[0.285345592],"iteration":522,"passed_time":4.63477348,"remaining_time":4.227126099},
{"learn":[0.2852146546],"iteration":523,"passed_time":4.64292886,"remaining_time":4.2176224},
{"learn":[0.2850021695],"iteration":524,"passed_time":4.652585808,"remaining_time":4.209482397},
{"learn":[0.2848438919],"iteration":525,"passed_time":4.660824383,"remaining_time":4.200058474},
{"learn":[0.2847561077],"iteration":526,"passed_time":4.669293749,"remaining_time":4.190846193},
{"learn":[0.2846122538],"iteration":527,"passed_time":4.67703848,"remaining_time":4.180988944},
{"learn":[0.2844299464],"iteration":528,"passed_time":4.686242089,"remaining_time":4.172438609},
{"learn":[0.2842904966],"iteration":529,"passed_time":4.693989361,"remaining_time":4.162594339},
{"learn":[0.2842113135],"iteration":530,"passed_time":4.702980661,"remaining_time":4.153856742},
{"learn":[0.2841284948],"iteration":531,"passed_time":4.713274867,"remaining_time":4.146264357},
{"learn":[0.2840185133],"iteration":532,"passed_time":4.721146231,"remaining_time":4.136539005},
{"learn":[0.2839263251],"iteration":533,"passed_time":4.7308977,"remaining_time":4.128461289},
{"learn":[0.2838164027],"iteration":534,"passed_time":4.738703611,"remaining_time":4.118686316},
{"learn":[0.2837028744],"iteration":535,"passed_time":4.749796112,"remaining_time":4.111763798},
{"learn":[0.2836288341],"iteration":536,"passed_time":4.757350768,"remaining_time":4.101775429},
{"learn":[0.2835364686],"iteration":537,"passed_time":4.766754448,"remaining_time":4.093383931},
{"learn":[0.2834175609],"iteration":538,"passed_time":4.775692193,"remaining_time":4.084590169},
{"learn":[0.2833507325],"iteration":539,"passed_time":4.783124208,"remaining_time":4.074513214},
{"learn":[0.2831687798],"iteration":540,"passed_time":4.791597777,"remaining_time":4.065329722},
{"learn":[0.2830980204],"iteration":541,"passed_time":4.800109292,"remaining_time":4.056180915},
{"learn":[0.2829777826],"iteration":542,"passed_time":4.809059194,"remaining_time":4.04740341},
{"learn":[0.2828887866],"iteration":543,"passed_time":4.816773195,"remaining_time":4.037589296},
{"learn":[0.2827306863],"iteration":544,"passed_time":4.825630637,"remaining_time":4.028737504},
{"learn":[0.2826147047],"iteration":545,"passed_time":4.833550402,"remaining_time":4.019106012},
{"learn":[0.2824775308],"iteration":546,"passed_time":4.842952022,"remaining_time":4.010707981},
{"learn":[0.2822972923],"iteration":547,"passed_time":4.850607433,"remaining_time":4.000865985},
{"learn":[0.2821544435],"iteration":548,"passed_time":4.860360664,"remaining_time":3.992755299},
{"learn":[0.2820145799],"iteration":549,"passed_time":4.868951951,"remaining_time":3.98368796},
{"learn":[0.2819012289],"iteration":550,"passed_time":4.877595582,"remaining_time":3.974665002},
{"learn":[0.2818125875],"iteration":551,"passed_time":4.887203177,"remaining_time":3.966425767},
{"learn":[0.2817354142],"iteration":552,"passed_time":4.895610593,"remaining_time":3.957211456},
{"learn":[0.2816457088],"iteration":553,"passed_time":4.903999397,"remaining_time":3.947985074},
{"learn":[0.2815189094],"iteration":554,"passed_time":4.911447922,"remaining_time":3.938007794},
{"learn":[0.2814308887],"iteration":555,"passed_time":4.919635524,"remaining_time":3.928629807},
{"learn":[0.2813301585],"iteration":556,"passed_time":4.927277587,"remaining_time":3.91882221},
{"learn":[0.2812086793],"iteration":557,"passed_time":4.935157807,"remaining_time":3.909211022},
{"learn":[0.2811331317],"iteration":558,"passed_time":4.94261834,"remaining_time":3.899274934},
{"learn":[0.281039909],"iteration":559,"passed_time":4.950320172,"remaining_time":3.889537278},
{"learn":[0.2809387946],"iteration":560,"passed_time":4.957864001,"remaining_time":3.879683238},
{"learn":[0.2807846845],"iteration":561,"passed_time":4.966069424,"remaining_time":3.870353039},
{"learn":[0.2806785454],"iteration":562,"passed_time":4.973820319,"remaining_time":3.860674031},
{"learn":[0.2805493814],"iteration":563,"passed_time":4.981959328,"remaining_time":3.851301892},
{"learn":[0.2803957147],"iteration":564,"passed_time":4.990060773,"remaining_time":3.841905197},
{"learn":[0.2802348361],"iteration":565,"passed_time":4.998711429,"remaining_time":3.832934205},
{"learn":[0.2800800758],"iteration":566,"passed_time":5.006820519,"remaining_time":3.823550767},
{"learn":[0.2799652765],"iteration":567,"passed_time":5.049509187,"remaining_time":3.840471776},
{"learn":[0.2798059939],"iteration":568,"passed_time":5.075610403,"remaining_time":3.844618776},
{"learn":[0.279671421],"iteration":569,"passed_time":5.097584206,"remaining_time":3.84554598},
{"learn":[0.2795886024],"iteration":570,"passed_time":5.10881882,"remaining_time":3.838324473},
{"learn":[0.279472207],"iteration":571,"passed_time":5.116697029,"remaining_time":3.828577497},
{"learn":[0.2793445504],"iteration":572,"passed_time":5.130153653,"remaining_time":3.822994084},
{"learn":[0.2792744117],"iteration":573,"passed_time":5.13945992,"remaining_time":3.814303007},
{"learn":[0.2791744204],"iteration":574,"passed_time":5.147740713,"remaining_time":3.804851831},
{"learn":[0.2790683405],"iteration":575,"passed_time":5.156385205,"remaining_time":3.795672442},
{"learn":[0.2789693541],"iteration":576,"passed_time":5.163785179,"remaining_time":3.785582549},
{"learn":[0.2788753334],"iteration":577,"passed_time":5.172098943,"remaining_time":3.776169125},
{"learn":[0.2787589085],"iteration":578,"passed_time":5.179560718,"remaining_time":3.766140004},
{"learn":[0.2786070152],"iteration":579,"passed_time":5.189277214,"remaining_time":3.757752465},
{"learn":[0.278440905],"iteration":580,"passed_time":5.197150239,"remaining_time":3.748030895},
{"learn":[0.2782797603],"iteration":581,"passed_time":5.205562598,"remaining_time":3.738703034},
{"learn":[0.2781498279],"iteration":582,"passed_time":5.213951562,"remaining_time":3.72936158},
{"learn":[0.277983363],"iteration":583,"passed_time":5.222408591,"remaining_time":3.720071873},
{"learn":[0.2778375584],"iteration":584,"passed_time":5.230870413,"remaining_time":3.710788412},
{"learn":[0.2776743743],"iteration":585,"passed_time":5.239392674,"remaining_time":3.701550456},
{"learn":[0.2775859399],"iteration":586,"passed_time":5.247375441,"remaining_time":3.691935361},
{"learn":[0.2774735051],"iteration":587,"passed_time":5.255208479,"remaining_time":3.682220907},
{"learn":[0.2773660951],"iteration":588,"passed_time":5.262731354,"remaining_time":3.672296412},
{"learn":[0.2772119259],"iteration":589,"passed_time":5.27069764,"remaining_time":3.662688191},
{"learn":[0.2770497763],"iteration":590,"passed_time":5.278342805,"remaining_time":3.652863295},
{"learn":[0.2769313711],"iteration":591,"passed_time":5.286948622,"remaining_time":3.643707834},
{"learn":[0.2767962957],"iteration":592,"passed_time":5.294534968,"remaining_time":3.633854523},
{"learn":[0.2767128268],"iteration":593,"passed_time":5.302927704,"remaining_time":3.624560013},
{"learn":[0.2766209046],"iteration":594,"passed_time":5.310378251,"remaining_time":3.614627213},
{"learn":[0.2765309331],"iteration":595,"passed_time":5.318590149,"remaining_time":3.605218826},
{"learn":[0.2764571589],"iteration":596,"passed_time":5.326459431,"remaining_time":3.595583167},
{"learn":[0.2763636407],"iteration":597,"passed_time":5.334501647,"remaining_time":3.586069669},
{"learn":[0.2762405063],"iteration":598,"passed_time":5.342347314,"remaining_time":3.576429504},
{"learn":[0.2761395397],"iteration":599,"passed_time":5.350986713,"remaining_time":3.567324475},
{"learn":[0.2760058239],"iteration":600,"passed_time":5.358717634,"remaining_time":3.557617863},
{"learn":[0.2758423147],"iteration":601,"passed_time":5.367875453,"remaining_time":3.54886118},
{"learn":[0.2757280179],"iteration":602,"passed_time":5.376030313,"remaining_time":3.539442843},
{"learn":[0.2756708251],"iteration":603,"passed_time":5.384299668,"remaining_time":3.530103756},
{"learn":[0.2755857602],"iteration":604,"passed_time":5.392153271,"remaining_time":3.520496763},
{"learn":[0.2755064292],"iteration":605,"passed_time":5.402001924,"remaining_time":3.51219267},
{"learn":[0.2754185563],"iteration":606,"passed_time":5.410217354,"remaining_time":3.502826063},
{"learn":[0.2753456393],"iteration":607,"passed_time":5.417490154,"remaining_time":3.492855494},
{"learn":[0.2752542491],"iteration":608,"passed_time":5.425450546,"remaining_time":3.483335244},
{"learn":[0.2751206516],"iteration":609,"passed_time":5.433610139,"remaining_time":3.473947466},
{"learn":[0.2749920787],"iteration":610,"passed_time":5.441971925,"remaining_time":3.464692437},
{"learn":[0.2748336238],"iteration":611,"passed_time":5.450204416,"remaining_time":3.455358355},
{"learn":[0.2747166668],"iteration":612,"passed_time":5.459058546,"remaining_time":3.446420322},
{"learn":[0.2745825964],"iteration":613,"passed_time":5.466776359,"remaining_time":3.436768199},
{"learn":[0.2745162114],"iteration":614,"passed_time":5.475324047,"remaining_time":3.427641883},
{"learn":[0.2743597959],"iteration":615,"passed_time":5.482917848,"remaining_time":3.417922814},
{"learn":[0.2742176859],"iteration":616,"passed_time":5.491907137,"remaining_time":3.409076877},
{"learn":[0.274124611],"iteration":617,"passed_time":5.499526295,"remaining_time":3.399383567},
{"learn":[0.2740673001],"iteration":618,"passed_time":5.507364567,"remaining_time":3.389831825},
{"learn":[0.2739429243],"iteration":619,"passed_time":5.515375882,"remaining_time":3.38039167},
{"learn":[0.2738746772],"iteration":620,"passed_time":5.523227083,"remaining_time":3.370858397},
{"learn":[0.2737214243],"iteration":621,"passed_time":5.531000632,"remaining_time":3.361283342},
{"learn":[0.273607157],"iteration":622,"passed_time":5.539238707,"remaining_time":3.351995173},
{"learn":[0.2734355492],"iteration":623,"passed_time":5.546985038,"remaining_time":3.342414062},
{"learn":[0.2733301786],"iteration":624,"passed_time":5.55564517,"remaining_time":3.333387102},
{"learn":[0.2732353894],"iteration":625,"passed_time":5.563743723,"remaining_time":3.324025803},
{"learn":[0.273078767],"iteration":626,"passed_time":5.573616983,"remaining_time":3.315724298},
{"learn":[0.2729710022],"iteration":627,"passed_time":5.581483523,"remaining_time":3.306229094},
{"learn":[0.2728765086],"iteration":628,"passed_time":5.590014671,"remaining_time":3.29713107},
{"learn":[0.2728129611],"iteration":629,"passed_time":5.597901064,"remaining_time":3.287656181},
{"learn":[0.2726434814],"iteration":630,"passed_time":5.60720494,"remaining_time":3.27901525},
{"learn":[0.2725134602],"iteration":631,"passed_time":5.615821043,"remaining_time":3.269971746},
{"learn":[0.2723978629],"iteration":632,"passed_time":5.624234423,"remaining_time":3.260812059},
{"learn":[0.2722829158],"iteration":633,"passed_time":5.633406131,"remaining_time":3.252092498},
{"learn":[0.2721687963],"iteration":634,"passed_time":5.641621611,"remaining_time":3.242821871},
{"learn":[0.2720961453],"iteration":635,"passed_time":5.650345215,"remaining_time":3.233845375},
{"learn":[0.27199509],"iteration":636,"passed_time":5.658610237,"remaining_time":3.224608346},
{"learn":[0.2718546352],"iteration":637,"passed_time":5.667268578,"remaining_time":3.215597532},
{"learn":[0.2717167224],"iteration":638,"passed_time":5.675600485,"remaining_time":3.206403404},
{"learn":[0.2716319825],"iteration":639,"passed_time":5.685500322,"remaining_time":3.198093931},
{"learn":[0.2715090255],"iteration":640,"passed_time":5.693076681,"remaining_time":3.188478204},
{"learn":[0.2713820192],"iteration":641,"passed_time":5.70378545,"remaining_time":3.180615563},
{"learn":[0.2713182352],"iteration":642,"passed_time":5.712255828,"remaining_time":3.171501291},
{"learn":[0.2711699479],"iteration":643,"passed_time":5.720335958,"remaining_time":3.162173294},
{"learn":[0.2710559466],"iteration":644,"passed_time":5.728929297,"remaining_time":3.153131628},
{"learn":[0.2709947046],"iteration":645,"passed_time":5.736405481,"remaining_time":3.143479164},
{"learn":[0.2709030484],"iteration":646,"passed_time":5.744672955,"remaining_time":3.134265151},
{"learn":[0.2708034414],"iteration":647,"passed_time":5.752498468,"remaining_time":3.124813983},
{"learn":[0.2707036275],"iteration":648,"passed_time":5.761500085,"remaining_time":3.116003898},
{"learn":[0.2705880301],"iteration":649,"passed_time":5.769360811,"remaining_time":3.106578898},
{"learn":[0.2704479892],"iteration":650,"passed_time":5.778349069,"remaining_time":3.097763172},
{"learn":[0.2702988447],"iteration":651,"passed_time":5.786177705,"remaining_time":3.088327977},
{"learn":[0.2702047944],"iteration":652,"passed_time":5.794454605,"remaining_time":3.079135908},
{"learn":[0.2701479268],"iteration":653,"passed_time":5.802168435,"remaining_time":3.069648744},
{"learn":[0.2700841724],"iteration":654,"passed_time":5.811779212,"remaining_time":3.06116615},
{"learn":[0.2699826737],"iteration":655,"passed_time":5.819850347,"remaining_time":3.051872743},
{"learn":[0.2699153725],"iteration":656,"passed_time":5.828369577,"remaining_time":3.042816994},
{"learn":[0.2697017346],"iteration":657,"passed_time":5.836481509,"remaining_time":3.033551179},
{"learn":[0.2695984035],"iteration":658,"passed_time":5.845431691,"remaining_time":3.02472262},
{"learn":[0.2695018113],"iteration":659,"passed_time":5.85321894,"remaining_time":3.015294605},
{"learn":[0.2694075245],"iteration":660,"passed_time":5.862229572,"remaining_time":3.006498979},
{"learn":[0.2693368242],"iteration":661,"passed_time":5.870935154,"remaining_time":2.997546952},
{"learn":[0.2692295324],"iteration":662,"passed_time":5.879561164,"remaining_time":2.988555222},
{"learn":[0.2690745652],"iteration":663,"passed_time":5.887837894,"remaining_time":2.97938785},
{"learn":[0.2689347015],"iteration":664,"passed_time":5.895628845,"remaining_time":2.969978441},
{"learn":[0.268814848],"iteration":665,"passed_time":5.904295922,"remaining_time":2.96101327},
{"learn":[0.2686790041],"iteration":666,"passed_time":5.912269262,"remaining_time":2.951702645},
{"learn":[0.268530037],"iteration":667,"passed_time":5.921985869,"remaining_time":2.943262438},
{"learn":[0.2684206762],"iteration":668,"passed_time":5.930337858,"remaining_time":2.934143245},
{"learn":[0.2683368526],"iteration":669,"passed_time":5.939346139,"remaining_time":2.925349591},
{"learn":[0.2682288514],"iteration":670,"passed_time":5.946782147,"remaining_time":2.915784391},
{"learn":[0.2681362789],"iteration":671,"passed_time":5.955226527,"remaining_time":2.90671771},
{"learn":[0.2680531943],"iteration":672,"passed_time":5.96251753,"remaining_time":2.89709247},
{"learn":[0.2679421783],"iteration":673,"passed_time":5.970655578,"remaining_time":2.887883855},
{"learn":[0.2678674878],"iteration":674,"passed_time":5.978575934,"remaining_time":2.878573598},
{"learn":[0.2677017027],"iteration":675,"passed_time":5.98705917,"remaining_time":2.869537235},
{"learn":[0.2675518193],"iteration":676,"passed_time":5.994431416,"remaining_time":2.859972448},
{"learn":[0.267448429],"iteration":677,"passed_time":6.002905077,"remaining_time":2.850937219},
{"learn":[0.2673698074],"iteration":678,"passed_time":6.010616876,"remaining_time":2.841543471},
{"learn":[0.267256486],"iteration":679,"passed_time":6.019406383,"remaining_time":2.832661827},
{"learn":[0.2671620514],"iteration":680,"passed_time":6.028221717,"remaining_time":2.823792552},
{"learn":[0.2670554985],"iteration":681,"passed_time":6.036484998,"remaining_time":2.814666026},
{"learn":[0.2668897135],"iteration":682,"passed_time":6.043609001,"remaining_time":2.805013255},
{"learn":[0.2667780176],"iteration":683,"passed_time":6.051295093,"remaining_time":2.795627557},
{"learn":[0.2666537306],"iteration":684,"passed_time":6.05894412,"remaining_time":2.786229778},
{"learn":[0.2665899466],"iteration":685,"passed_time":6.067586811,"remaining_time":2.777291922},
{"learn":[0.266483039],"iteration":686,"passed_time":6.076065994,"remaining_time":2.768280431},
{"learn":[0.2663475498],"iteration":687,"passed_time":6.086626796,"remaining_time":2.760214477},
{"learn":[0.266193558],"iteration":688,"passed_time":6.094866601,"remaining_time":2.751093633},
{"learn":[0.2660938623],"iteration":689,"passed_time":6.103454196,"remaining_time":2.742131595},
{"learn":[0.2660329454],"iteration":690,"passed_time":6.110703721,"remaining_time":2.732572286},
{"learn":[0.2659452794],"iteration":691,"passed_time":6.119391541,"remaining_time":2.723659819},
{"learn":[0.2658683721],"iteration":692,"passed_time":6.127935047,"remaining_time":2.714684068},
{"learn":[0.2657740854],"iteration":693,"passed_time":6.135900642,"remaining_time":2.70545475},
{"learn":[0.2656642517],"iteration":694,"passed_time":6.144455956,"remaining_time":2.696487865},
{"learn":[0.2655089298],"iteration":695,"passed_time":6.152649171,"remaining_time":2.687364006},
{"learn":[0.2654269978],"iteration":696,"passed_time":6.161415943,"remaining_time":2.678492153},
{"learn":[0.2653013807],"iteration":697,"passed_time":6.168959181,"remaining_time":2.669091222},
{"learn":[0.265178867],"iteration":698,"passed_time":6.177847163,"remaining_time":2.660274672},
{"learn":[0.2651242457],"iteration":699,"passed_time":6.185572571,"remaining_time":2.650959673},
{"learn":[0.2650110129],"iteration":700,"passed_time":6.194261882,"remaining_time":2.642060346},
{"learn":[0.2648825879],"iteration":701,"passed_time":6.20192701,"remaining_time":2.63272685},
{"learn":[0.2647923209],"iteration":702,"passed_time":6.209398861,"remaining_time":2.623316446},
{"learn":[0.2647065465],"iteration":703,"passed_time":6.217664844,"remaining_time":2.614245446},
{"learn":[0.2646515705],"iteration":704,"passed_time":6.226294336,"remaining_time":2.605328836},
{"learn":[0.2645136281],"iteration":705,"passed_time":6.234328767,"remaining_time":2.596165237},
{"learn":[0.2643407198],"iteration":706,"passed_time":6.24248808,"remaining_time":2.587056588},
{"learn":[0.2642753102],"iteration":707,"passed_time":6.250333247,"remaining_time":2.577821056},
{"learn":[0.2642014769],"iteration":708,"passed_time":6.259073491,"remaining_time":2.568956821},
{"learn":[0.2641055941],"iteration":709,"passed_time":6.267331969,"remaining_time":2.559896157},
{"learn":[0.2640079378],"iteration":710,"passed_time":6.277546813,"remaining_time":2.551632952},
{"learn":[0.2639045771],"iteration":711,"passed_time":6.285106382,"remaining_time":2.542290222},
{"learn":[0.2638148421],"iteration":712,"passed_time":6.294380508,"remaining_time":2.533642645},
{"learn":[0.263729452],"iteration":713,"passed_time":6.302592566,"remaining_time":2.52456789},
{"learn":[0.2636114605],"iteration":714,"passed_time":6.310239242,"remaining_time":2.515270187},
{"learn":[0.2634740206],"iteration":715,"passed_time":6.317628398,"remaining_time":2.505874951},
{"learn":[0.2633814777],"iteration":716,"passed_time":6.326504472,"remaining_time":2.497072198},
{"learn":[0.2632605601],"iteration":717,"passed_time":6.334571144,"remaining_time":2.487951341},
{"learn":[0.2631327558],"iteration":718,"passed_time":6.342630372,"remaining_time":2.478830507},
{"learn":[0.263056617],"iteration":719,"passed_time":6.351172036,"remaining_time":2.469900236},
{"learn":[0.2629649312],"iteration":720,"passed_time":6.358794896,"remaining_time":2.460615501},
{"learn":[0.2628647035],"iteration":721,"passed_time":6.366093153,"remaining_time":2.451210383},
{"learn":[0.2627558452],"iteration":722,"passed_time":6.373338726,"remaining_time":2.441790909},
{"learn":[0.262645243],"iteration":723,"passed_time":6.380822174,"remaining_time":2.432468122},
{"learn":[0.2625449857],"iteration":724,"passed_time":6.389448784,"remaining_time":2.423584022},
{"learn":[0.2624525315],"iteration":725,"passed_time":6.3967456,"remaining_time":2.414198753},
{"learn":[0.2623977329],"iteration":726,"passed_time":6.404125191,"remaining_time":2.404850312},
{"learn":[0.2622939879],"iteration":727,"passed_time":6.411067054,"remaining_time":2.395343734},
{"learn":[0.2622029228],"iteration":728,"passed_time":6.419607247,"remaining_time":2.386438359},
{"learn":[0.2620584779],"iteration":729,"passed_time":6.426932892,"remaining_time":2.377084768},
{"learn":[0.261998359],"iteration":730,"passed_time":6.434693503,"remaining_time":2.367896788},
{"learn":[0.2618177659],"iteration":731,"passed_time":6.441632994,"remaining_time":2.35841208},
{"learn":[0.2617407995],"iteration":732,"passed_time":6.449622956,"remaining_time":2.349316957},
{"learn":[0.2616289263],"iteration":733,"passed_time":6.457474036,"remaining_time":2.340174514},
{"learn":[0.2615102846],"iteration":734,"passed_time":6.465843117,"remaining_time":2.331222348},
{"learn":[0.2614270226],"iteration":735,"passed_time":6.473553905,"remaining_time":2.32203564},
{"learn":[0.2612813659],"iteration":736,"passed_time":6.481770666,"remaining_time":2.313033494},
{"learn":[0.2612029808],"iteration":737,"passed_time":6.489742876,"remaining_time":2.303946658},
{"learn":[0.2610900731],"iteration":738,"passed_time":6.49931892,"remaining_time":2.29542928},
{"learn":[0.2609912937],"iteration":739,"passed_time":6.507619986,"remaining_time":2.286461076},
{"learn":[0.2609262683],"iteration":740,"passed_time":6.516259645,"remaining_time":2.27761302},
{"learn":[0.2608034],"iteration":741,"passed_time":6.524250977,"remaining_time":2.268540097},
{"learn":[0.2607196651],"iteration":742,"passed_time":6.532819669,"remaining_time":2.259669791},
{"learn":[0.2606435559],"iteration":743,"passed_time":6.543202604,"remaining_time":2.251424552},
{"learn":[0.2605337517],"iteration":744,"passed_time":6.550598785,"remaining_time":2.242151262},
{"learn":[0.2604777708],"iteration":745,"passed_time":6.558599604,"remaining_time":2.233088873},
{"learn":[0.2604290313],"iteration":746,"passed_time":6.566329985,"remaining_time":2.223937732},
{"learn":[0.2603541931],"iteration":747,"passed_time":6.576377839,"remaining_time":2.215571144},
{"learn":[0.2601722403],"iteration":748,"passed_time":6.584335249,"remaining_time":2.206499529},
{"learn":[0.2600100316],"iteration":749,"passed_time":6.59539659,"remaining_time":2.19846553},
{"learn":[0.2599630065],"iteration":750,"passed_time":6.604119353,"remaining_time":2.189648094},
{"learn":[0.259835143],"iteration":751,"passed_time":6.612171676,"remaining_time":2.180609808},
{"learn":[0.2597230925],"iteration":752,"passed_time":6.621640459,"remaining_time":2.17203877},
{"learn":[0.2596302836],"iteration":753,"passed_time":6.629039222,"remaining_time":2.162789985},
{"learn":[0.2594995827],"iteration":754,"passed_time":6.638740209,"remaining_time":2.15429318},
{"learn":[0.2593871775],"iteration":755,"passed_time":6.647100584,"remaining_time":2.145360506},
{"learn":[0.2592434715],"iteration":756,"passed_time":6.656261055,"remaining_time":2.136686177},
{"learn":[0.2591477069],"iteration":757,"passed_time":6.664264906,"remaining_time":2.127641302},
{"learn":[0.2590685533],"iteration":758,"passed_time":6.674120053,"remaining_time":2.119187},
{"learn":[0.2589666408],"iteration":759,"passed_time":6.682117139,"remaining_time":2.110142255},
{"learn":[0.2588500681],"iteration":760,"passed_time":6.692485865,"remaining_time":2.101845101},
{"learn":[0.2587630524],"iteration":761,"passed_time":6.700880492,"remaining_time":2.092925928},
{"learn":[0.2586182232],"iteration":762,"passed_time":6.709190574,"remaining_time":2.083981869},
{"learn":[0.2584723891],"iteration":763,"passed_time":6.720174324,"remaining_time":2.075865367},
{"learn":[0.2583939448],"iteration":764,"passed_time":6.728747959,"remaining_time":2.067001007},
{"learn":[0.2583008699],"iteration":765,"passed_time":6.738483588,"remaining_time":2.058492375},
{"learn":[0.2582321795],"iteration":766,"passed_time":6.746289919,"remaining_time":2.04939446},
{"learn":[0.2581137447],"iteration":767,"passed_time":6.755547324,"remaining_time":2.040738254},
{"learn":[0.2580482464],"iteration":768,"passed_time":6.764279463,"remaining_time":2.0319227},
{"learn":[0.2579583341],"iteration":769,"passed_time":6.77343384,"remaining_time":2.023233485},
{"learn":[0.2578640474],"iteration":770,"passed_time":6.78160331,"remaining_time":2.014250529},
{"learn":[0.2577624305],"iteration":771,"passed_time":6.789649668,"remaining_time":2.005233322},
{"learn":[0.2576799665],"iteration":772,"passed_time":6.799442995,"remaining_time":1.996731643},
{"learn":[0.2576039164],"iteration":773,"passed_time":6.807006577,"remaining_time":1.987575564},
{"learn":[0.2574850678],"iteration":774,"passed_time":6.81638273,"remaining_time":1.978949825},
{"learn":[0.2573628202],"iteration":775,"passed_time":6.824235861,"remaining_time":1.969882517},
{"learn":[0.2572892233],"iteration":776,"passed_time":6.832854076,"remaining_time":1.961037914},
{"learn":[0.257158611],"iteration":777,"passed_time":6.840405609,"remaining_time":1.951889518},
{"learn":[0.2570611912],"iteration":778,"passed_time":6.848639281,"remaining_time":1.942938743},
{"learn":[0.2570067768],"iteration":779,"passed_time":6.856763291,"remaining_time":1.933958877},
{"learn":[0.2569151502],"iteration":780,"passed_time":6.865256854,"remaining_time":1.925084828},
{"learn":[0.2568220457],"iteration":781,"passed_time":6.873164981,"remaining_time":1.91604855},
{"learn":[0.2567337295],"iteration":782,"passed_time":6.882145644,"remaining_time":1.907312394},
{"learn":[0.2566525069],"iteration":783,"passed_time":6.889983876,"remaining_time":1.898260864},
{"learn":[0.2565544073],"iteration":784,"passed_time":6.898505387,"remaining_time":1.889399565},
{"learn":[0.2564769385],"iteration":785,"passed_time":6.905835915,"remaining_time":1.880214868},
{"learn":[0.2564205142],"iteration":786,"passed_time":6.91418007,"remaining_time":1.871309218},
{"learn":[0.2562779905],"iteration":787,"passed_time":6.921890878,"remaining_time":1.862234602},
{"learn":[0.256182019],"iteration":788,"passed_time":6.930426458,"remaining_time":1.853384008},
{"learn":[0.2561133877],"iteration":789,"passed_time":6.938620244,"remaining_time":1.844443356},
{"learn":[0.2560197512],"iteration":790,"passed_time":6.946852565,"remaining_time":1.835514774},
{"learn":[0.2559359867],"iteration":791,"passed_time":6.954134681,"remaining_time":1.826338401},
{"learn":[0.2557966551],"iteration":792,"passed_time":6.962542147,"remaining_time":1.81746056},
{"learn":[0.2556702399],"iteration":793,"passed_time":6.97158292,"remaining_time":1.808748213},
{"learn":[0.2555915888],"iteration":794,"passed_time":6.979820024,"remaining_time":1.799827805},
{"learn":[0.255505578],"iteration":795,"passed_time":6.988407428,"remaining_time":1.790998889},
{"learn":[0.255457075],"iteration":796,"passed_time":6.996312424,"remaining_time":1.781996765},
{"learn":[0.2554155179],"iteration":797,"passed_time":7.004678563,"remaining_time":1.773114122},
{"learn":[0.2553133394],"iteration":798,"passed_time":7.013476786,"remaining_time":1.764341469},
{"learn":[0.2552262646],"iteration":799,"passed_time":7.023077856,"remaining_time":1.755769464},
{"learn":[0.2551591111],"iteration":800,"passed_time":7.030817253,"remaining_time":1.746732376},
{"learn":[0.2550463808],"iteration":801,"passed_time":7.040972468,"remaining_time":1.738294948},
{"learn":[0.2549502911],"iteration":802,"passed_time":7.051926778,"remaining_time":1.730049284},
{"learn":[0.2548667335],"iteration":803,"passed_time":7.060756972,"remaining_time":1.721279063},
{"learn":[0.2547594417],"iteration":804,"passed_time":7.07473576,"remaining_time":1.713755867},
{"learn":[0.2546909877],"iteration":805,"passed_time":7.084265464,"remaining_time":1.705145782},
{"learn":[0.2546314304],"iteration":806,"passed_time":7.092904582,"remaining_time":1.696320427},
{"learn":[0.2545482866],"iteration":807,"passed_time":7.102630955,"remaining_time":1.68775389},
{"learn":[0.2544438914],"iteration":808,"passed_time":7.110599262,"remaining_time":1.678769418},
{"learn":[0.2543823242],"iteration":809,"passed_time":7.120970319,"remaining_time":1.670351062},
{"learn":[0.2542587169],"iteration":810,"passed_time":7.128768064,"remaining_time":1.661328193},
{"learn":[0.2541683022],"iteration":811,"passed_time":7.1379055,"remaining_time":1.652618515},
{"learn":[0.2540798677],"iteration":812,"passed_time":7.146346888,"remaining_time":1.643747685},
{"learn":[0.2539650093],"iteration":813,"passed_time":7.154281233,"remaining_time":1.634762051},
{"learn":[0.2538428503],"iteration":814,"passed_time":7.162670588,"remaining_time":1.625882281},
{"learn":[0.2536906023],"iteration":815,"passed_time":7.170490548,"remaining_time":1.61687532},
{"learn":[0.2535959609],"iteration":816,"passed_time":7.178942733,"remaining_time":1.608012877},
{"learn":[0.253503152],"iteration":817,"passed_time":7.187117696,"remaining_time":1.599089756},
{"learn":[0.2534520184],"iteration":818,"passed_time":7.195604454,"remaining_time":1.59023737},
{"learn":[0.2533567267],"iteration":819,"passed_time":7.203407323,"remaining_time":1.581235754},
{"learn":[0.2532405973],"iteration":820,"passed_time":7.212925059,"remaining_time":1.572610945},
{"learn":[0.2531814538],"iteration":821,"passed_time":7.220926198,"remaining_time":1.563655551},
{"learn":[0.2530999948],"iteration":822,"passed_time":7.230604879,"remaining_time":1.555063261},
{"learn":[0.2530209594],"iteration":823,"passed_time":7.238530599,"remaining_time":1.546093914},
{"learn":[0.2529131947],"iteration":824,"passed_time":7.248413405,"remaining_time":1.537542237},
{"learn":[0.2528167799],"iteration":825,"passed_time":7.25656177,"remaining_time":1.528621971},
{"learn":[0.2527487397],"iteration":826,"passed_time":7.265499735,"remaining_time":1.519868748},
{"learn":[0.2526851922],"iteration":827,"passed_time":7.274657164,"remaining_time":1.511160667},
{"learn":[0.2526021962],"iteration":828,"passed_time":7.283572624,"remaining_time":1.502401591},
{"learn":[0.2524713179],"iteration":829,"passed_time":7.292700304,"remaining_time":1.493685604},
{"learn":[0.2523942924],"iteration":830,"passed_time":7.300890698,"remaining_time":1.484778012},
{"learn":[0.2522992963],"iteration":831,"passed_time":7.309955937,"remaining_time":1.476048795},
{"learn":[0.2521970292],"iteration":832,"passed_time":7.318013113,"remaining_time":1.467116674},
{"learn":[0.2520873137],"iteration":833,"passed_time":7.328018709,"remaining_time":1.458574467},
{"learn":[0.2520022783],"iteration":834,"passed_time":7.33651028,"remaining_time":1.449729576},
{"learn":[0.2518841981],"iteration":835,"passed_time":7.344975755,"remaining_time":1.440880411},
{"learn":[0.2518197048],"iteration":836,"passed_time":7.353694714,"remaining_time":1.432081527},
{"learn":[0.2517427384],"iteration":837,"passed_time":7.362137503,"remaining_time":1.423229446},
{"learn":[0.2517003242],"iteration":838,"passed_time":7.369669894,"remaining_time":1.414203639},
{"learn":[0.2516204021],"iteration":839,"passed_time":7.378325964,"remaining_time":1.405395422},
{"learn":[0.2515197015],"iteration":840,"passed_time":7.387029374,"remaining_time":1.396596517},
{"learn":[0.2514343114],"iteration":841,"passed_time":7.395202466,"remaining_time":1.387698325},
{"learn":[0.2513603303],"iteration":842,"passed_time":7.404282454,"remaining_time":1.378970754},
{"learn":[0.2512678761],"iteration":843,"passed_time":7.413056992,"remaining_time":1.370185889},
{"learn":[0.2511938063],"iteration":844,"passed_time":7.422214991,"remaining_time":1.361471389},
{"learn":[0.2511455693],"iteration":845,"passed_time":7.43033812,"remaining_time":1.352567459},
{"learn":[0.2510372134],"iteration":846,"passed_time":7.43935936,"remaining_time":1.343827606},
{"learn":[0.2509511731],"iteration":847,"passed_time":7.447677137,"remaining_time":1.334960996},
{"learn":[0.250887862],"iteration":848,"passed_time":7.456895616,"remaining_time":1.326255875},
{"learn":[0.2508309648],"iteration":849,"passed_time":7.492964713,"remaining_time":1.322287891},
{"learn":[0.2507738608],"iteration":850,"passed_time":7.518339272,"remaining_time":1.316371976},
{"learn":[0.2507215745],"iteration":851,"passed_time":7.5466654,"remaining_time":1.310923098},
{"learn":[0.2506185093],"iteration":852,"passed_time":7.5564023,"remaining_time":1.302217043},
{"learn":[0.2504741235],"iteration":853,"passed_time":7.56486214,"remaining_time":1.293290249},
{"learn":[0.2503181217],"iteration":854,"passed_time":7.573880288,"remaining_time":1.28445923},
{"learn":[0.250234978],"iteration":855,"passed_time":7.582679951,"remaining_time":1.27559102},
{"learn":[0.2501429671],"iteration":856,"passed_time":7.591195278,"remaining_time":1.266675525},
{"learn":[0.2500702569],"iteration":857,"passed_time":7.601157847,"remaining_time":1.258000483},
{"learn":[0.2500230249],"iteration":858,"passed_time":7.610825171,"remaining_time":1.24927398},
{"learn":[0.2499230041],"iteration":859,"passed_time":7.618959657,"remaining_time":1.240295758},
{"learn":[0.2498371411],"iteration":860,"passed_time":7.628492293,"remaining_time":1.231545213},
{"learn":[0.2497483223],"iteration":861,"passed_time":7.639341354,"remaining_time":1.223003604},
{"learn":[0.2496180943],"iteration":862,"passed_time":7.648107085,"remaining_time":1.214125922},
{"learn":[0.2494731765],"iteration":863,"passed_time":7.655952112,"remaining_time":1.205103573},
{"learn":[0.2493489485],"iteration":864,"passed_time":7.66439361,"remaining_time":1.196177037},
{"learn":[0.2492871744],"iteration":865,"passed_time":7.672934184,"remaining_time":1.187266952},
{"learn":[0.2492021981],"iteration":866,"passed_time":7.681476929,"remaining_time":1.178358052},
{"learn":[0.2491157439],"iteration":867,"passed_time":7.689561382,"remaining_time":1.169380302},
{"learn":[0.249042354],"iteration":868,"passed_time":7.697961213,"remaining_time":1.160452151},
{"learn":[0.2488982933],"iteration":869,"passed_time":7.70614139,"remaining_time":1.151492392},
{"learn":[0.2488396522],"iteration":870,"passed_time":7.713637497,"remaining_time":1.142433108},
{"learn":[0.2487736515],"iteration":871,"passed_time":7.721412788,"remaining_time":1.133418391},
{"learn":[0.2486654434],"iteration":872,"passed_time":7.729636523,"remaining_time":1.124471751},
{"learn":[0.2485418361],"iteration":873,"passed_time":7.737880642,"remaining_time":1.115529703},
{"learn":[0.2484435887],"iteration":874,"passed_time":7.745763473,"remaining_time":1.106537639},
{"learn":[0.2483537355],"iteration":875,"passed_time":7.753638809,"remaining_time":1.097547046},
{"learn":[0.2482400003],"iteration":876,"passed_time":7.761107648,"remaining_time":1.088501985},
{"learn":[0.2481335361],"iteration":877,"passed_time":7.769290847,"remaining_time":1.079559776},
{"learn":[0.2480850626],"iteration":878,"passed_time":7.776881466,"remaining_time":1.070537722},
{"learn":[0.2480073869],"iteration":879,"passed_time":7.784551868,"remaining_time":1.0615298},
{"learn":[0.2478955137],"iteration":880,"passed_time":7.792197713,"remaining_time":1.052521598},
{"learn":[0.2478239415],"iteration":881,"passed_time":7.799806865,"remaining_time":1.043511576},
{"learn":[0.2477448175],"iteration":882,"passed_time":7.807451659,"remaining_time":1.03450945},
{"learn":[0.2476318359],"iteration":883,"passed_time":7.815362699,"remaining_time":1.025545332},
{"learn":[0.247550702],"iteration":884,"passed_time":7.823331167,"remaining_time":1.016591056},
{"learn":[0.2474736618],"iteration":885,"passed_time":7.830772257,"remaining_time":1.007571148},
{"learn":[0.2473942865],"iteration":886,"passed_time":7.840704105,"remaining_time":0.9988721127},
{"learn":[0.2473038422],"iteration":887,"passed_time":7.850378264,"remaining_time":0.9901377991},
{"learn":[0.2471933434],"iteration":888,"passed_time":7.858422191,"remaining_time":0.9811978214},
{"learn":[0.2471300471],"iteration":889,"passed_time":7.867028468,"remaining_time":0.9723293612},
{"learn":[0.2470337949],"iteration":890,"passed_time":7.875152448,"remaining_time":0.963402488},
{"learn":[0.2469467643],"iteration":891,"passed_time":7.883861722,"remaining_time":0.9545482803},
{"learn":[0.2468364873],"iteration":892,"passed_time":7.892730431,"remaining_time":0.9457135007},
{"learn":[0.2467443434],"iteration":893,"passed_time":7.901535018,"remaining_time":0.9368710425},
{"learn":[0.2466456379],"iteration":894,"passed_time":7.909649852,"remaining_time":0.927947748},
{"learn":[0.2465305578],"iteration":895,"passed_time":7.918887844,"remaining_time":0.9191566248},
{"learn":[0.2464497342],"iteration":896,"passed_time":7.92782719,"remaining_time":0.9103302124},
{"learn":[0.2463383044],"iteration":897,"passed_time":7.935924792,"remaining_time":0.9014079385},
{"learn":[0.246267412],"iteration":898,"passed_time":7.945117654,"remaining_time":0.8926105485},
{"learn":[0.2461906082],"iteration":899,"passed_time":7.952866287,"remaining_time":0.8836518097},
{"learn":[0.2461043757],"iteration":900,"passed_time":7.961501273,"remaining_time":0.8747931476},
{"learn":[0.245936965],"iteration":901,"passed_time":7.969323414,"remaining_time":0.8658466681},
{"learn":[0.2458004561],"iteration":902,"passed_time":7.977935805,"remaining_time":0.8569875671},
{"learn":[0.2457209479],"iteration":903,"passed_time":7.985959899,"remaining_time":0.848066538},
{"learn":[0.2456412327],"iteration":904,"passed_time":7.994972593,"remaining_time":0.8392512667},
{"learn":[0.2455669856],"iteration":905,"passed_time":8.002855234,"remaining_time":0.8303183135},
{"learn":[0.2454912754],"iteration":906,"passed_time":8.012687157,"remaining_time":0.8215875475},
{"learn":[0.2454069198],"iteration":907,"passed_time":8.020499041,"remaining_time":0.8126496826},
{"learn":[0.2453556236],"iteration":908,"passed_time":8.030809488,"remaining_time":0.8039644262},
{"learn":[0.2452881746],"iteration":909,"passed_time":8.041938783,"remaining_time":0.7953565829},
{"learn":[0.2452033756],"iteration":910,"passed_time":8.050900063,"remaining_time":0.7865314002},
{"learn":[0.2451281679],"iteration":911,"passed_time":8.060625065,"remaining_time":0.7777796115},
{"learn":[0.2450456448],"iteration":912,"passed_time":8.06869592,"remaining_time":0.7688680669},
{"learn":[0.2449579641],"iteration":913,"passed_time":8.078338938,"remaining_time":0.7601062896},
{"learn":[0.2448915643],"iteration":914,"passed_time":8.086061324,"remaining_time":0.7511641667},
{"learn":[0.2447938637],"iteration":915,"passed_time":8.095196788,"remaining_time":0.7423542906},
{"learn":[0.2447039071],"iteration":916,"passed_time":8.10376551,"remaining_time":0.7334924072},
{"learn":[0.2446241771],"iteration":917,"passed_time":8.112159928,"remaining_time":0.7246155927},
{"learn":[0.2445514522],"iteration":918,"passed_time":8.120471241,"remaining_time":0.7157325033},
{"learn":[0.2444903727],"iteration":919,"passed_time":8.128982765,"remaining_time":0.7068680665},
{"learn":[0.244384337],"iteration":920,"passed_time":8.138413464,"remaining_time":0.6980832396},
{"learn":[0.2442733063],"iteration":921,"passed_time":8.146145556,"remaining_time":0.6891533117},
{"learn":[0.2441957192],"iteration":922,"passed_time":8.15471704,"remaining_time":0.6802960044},
{"learn":[0.2441088513],"iteration":923,"passed_time":8.16251994,"remaining_time":0.671376099},
{"learn":[0.2440528112],"iteration":924,"passed_time":8.170583599,"remaining_time":0.6624797512},
{"learn":[0.2439790961],"iteration":925,"passed_time":8.178749806,"remaining_time":0.653593397},
{"learn":[0.2439080412],"iteration":926,"passed_time":8.187686412,"remaining_time":0.6447692643},
{"learn":[0.2438493114],"iteration":927,"passed_time":8.195257758,"remaining_time":0.635838964},
{"learn":[0.2437489803],"iteration":928,"passed_time":8.203714678,"remaining_time":0.6269792703},
{"learn":[0.2436824919],"iteration":929,"passed_time":8.211552711,"remaining_time":0.61807386},
{"learn":[0.2436080378],"iteration":930,"passed_time":8.220811467,"remaining_time":0.6092760378},
{"learn":[0.2435424361],"iteration":931,"passed_time":8.228370754,"remaining_time":0.600353231},
{"learn":[0.2434679526],"iteration":932,"passed_time":8.237138487,"remaining_time":0.5915201271},
{"learn":[0.2433743604],"iteration":933,"passed_time":8.244744366,"remaining_time":0.5826050623},
{"learn":[0.2432976896],"iteration":934,"passed_time":8.253740179,"remaining_time":0.5737894242},
{"learn":[0.2431638408],"iteration":935,"passed_time":8.262723303,"remaining_time":0.5649725336},
{"learn":[0.2430975002],"iteration":936,"passed_time":8.271616118,"remaining_time":0.5561492161},
{"learn":[0.2430541105],"iteration":937,"passed_time":8.280676674,"remaining_time":0.5473368377},
{"learn":[0.2429368432],"iteration":938,"passed_time":8.28902337,"remaining_time":0.5384775565},
{"learn":[0.2428469605],"iteration":939,"passed_time":8.298624891,"remaining_time":0.5296994611},
{"learn":[0.2427146043],"iteration":940,"passed_time":8.306647003,"remaining_time":0.5208205879},
{"learn":[0.2426104899],"iteration":941,"passed_time":8.315596736,"remaining_time":0.5120006483},
{"learn":[0.2424954541],"iteration":942,"passed_time":8.323614356,"remaining_time":0.5031240915},
{"learn":[0.2424246504],"iteration":943,"passed_time":8.333314802,"remaining_time":0.4943491831},
{"learn":[0.2423696892],"iteration":944,"passed_time":8.342132467,"remaining_time":0.4855209373},
{"learn":[0.2423142403],"iteration":945,"passed_time":8.351047237,"remaining_time":0.4766982566},
{"learn":[0.2422681019],"iteration":946,"passed_time":8.359218488,"remaining_time":0.4678337696},
{"learn":[0.2421859335],"iteration":947,"passed_time":8.367439121,"remaining_time":0.4589734539},
{"learn":[0.2420988291],"iteration":948,"passed_time":8.375574588,"remaining_time":0.4501099094},
{"learn":[0.2420503852],"iteration":949,"passed_time":8.383414391,"remaining_time":0.4412323364},
{"learn":[0.2419612118],"iteration":950,"passed_time":8.391558234,"remaining_time":0.4323726114},
{"learn":[0.2419041816],"iteration":951,"passed_time":8.39947879,"remaining_time":0.4235031323},
{"learn":[0.2417987223],"iteration":952,"passed_time":8.407975034,"remaining_time":0.4146640363},
{"learn":[0.2417295147],"iteration":953,"passed_time":8.416095602,"remaining_time":0.4058075447},
{"learn":[0.2416731347],"iteration":954,"passed_time":8.424081401,"remaining_time":0.396946244},
{"learn":[0.2415940846],"iteration":955,"passed_time":8.431911317,"remaining_time":0.3880796004},
{"learn":[0.2415143694],"iteration":956,"passed_time":8.44011595,"remaining_time":0.3792319601},
{"learn":[0.2414530683],"iteration":957,"passed_time":8.448083637,"remaining_time":0.3703752743},
{"learn":[0.2413527814],"iteration":958,"passed_time":8.457694474,"remaining_time":0.3615906918},
{"learn":[0.2412842388],"iteration":959,"passed_time":8.465799711,"remaining_time":0.3527416546},
{"learn":[0.2411950358],"iteration":960,"passed_time":8.474695949,"remaining_time":0.3439262664},
{"learn":[0.2410909657],"iteration":961,"passed_time":8.482833097,"remaining_time":0.3350807252},
{"learn":[0.2410185807],"iteration":962,"passed_time":8.491245736,"remaining_time":0.3262472401},
{"learn":[0.2409061164],"iteration":963,"passed_time":8.499427944,"remaining_time":0.3174060228},
{"learn":[0.2407670656],"iteration":964,"passed_time":8.508979673,"remaining_time":0.308615843},
{"learn":[0.2407036216],"iteration":965,"passed_time":8.516997032,"remaining_time":0.2997700819},
{"learn":[0.240596448],"iteration":966,"passed_time":8.52701998,"remaining_time":0.2909944771},
{"learn":[0.2405260137],"iteration":967,"passed_time":8.535592124,"remaining_time":0.2821683347},
{"learn":[0.2404761215],"iteration":968,"passed_time":8.544068346,"remaining_time":0.2733396478},
{"learn":[0.240376751],"iteration":969,"passed_time":8.553562536,"remaining_time":0.2645431712},
{"learn":[0.2403135581],"iteration":970,"passed_time":8.561455564,"remaining_time":0.255697437},
{"learn":[0.2402093402],"iteration":971,"passed_time":8.570732251,"remaining_time":0.2468935216},
{"learn":[0.2401170634],"iteration":972,"passed_time":8.578974999,"remaining_time":0.2380599435},
{"learn":[0.2400159785],"iteration":973,"passed_time":8.588982887,"remaining_time":0.2292746972},
{"learn":[0.2399361156],"iteration":974,"passed_time":8.596816396,"remaining_time":0.2204311896},
{"learn":[0.2398473707],"iteration":975,"passed_time":8.606556958,"remaining_time":0.2116366465},
{"learn":[0.2397486061],"iteration":976,"passed_time":8.615980712,"remaining_time":0.2028327087},
{"learn":[0.2396635707],"iteration":977,"passed_time":8.623651624,"remaining_time":0.1939880733},
{"learn":[0.2396023286],"iteration":978,"passed_time":8.632283098,"remaining_time":0.1851664403},
{"learn":[0.2395475152],"iteration":979,"passed_time":8.640485339,"remaining_time":0.1763364355},
{"learn":[0.2394939727],"iteration":980,"passed_time":8.654786108,"remaining_time":0.1676258268},
{"learn":[0.2394020801],"iteration":981,"passed_time":8.666825171,"remaining_time":0.1588623758},
{"learn":[0.2393257197],"iteration":982,"passed_time":8.675159329,"remaining_time":0.1500281878},
{"learn":[0.2392265708],"iteration":983,"passed_time":8.684962963,"remaining_time":0.14121891},
{"learn":[0.2391238012],"iteration":984,"passed_time":8.692862305,"remaining_time":0.1323786138},
{"learn":[0.239062766],"iteration":985,"passed_time":8.701965729,"remaining_time":0.1235573227},
{"learn":[0.2389571294],"iteration":986,"passed_time":8.710611701,"remaining_time":0.1147294348},
{"learn":[0.2388507243],"iteration":987,"passed_time":8.719813329,"remaining_time":0.1059086639},
{"learn":[0.2387795215],"iteration":988,"passed_time":8.72813587,"remaining_time":0.09707734537},
{"learn":[0.2386844958],"iteration":989,"passed_time":8.735823773,"remaining_time":0.08824064417},
{"learn":[0.238614032],"iteration":990,"passed_time":8.744356101,"remaining_time":0.07941393028},
{"learn":[0.2385085431],"iteration":991,"passed_time":8.751522331,"remaining_time":0.07057679299},
{"learn":[0.2384629958],"iteration":992,"passed_time":8.759669546,"remaining_time":0.06174993638},
{"learn":[0.238372921],"iteration":993,"passed_time":8.767622403,"remaining_time":0.05292327406},
{"learn":[0.2383225707],"iteration":994,"passed_time":8.775834951,"remaining_time":0.04409967312},
{"learn":[0.2382173478],"iteration":995,"passed_time":8.782955902,"remaining_time":0.03527291527},
{"learn":[0.2381249232],"iteration":996,"passed_time":8.790604809,"remaining_time":0.02645116793},
{"learn":[0.2380733462],"iteration":997,"passed_time":8.798403965,"remaining_time":0.01763207208},
{"learn":[0.2380074489],"iteration":998,"passed_time":8.806171971,"remaining_time":0.008814986958},
{"learn":[0.2379557834],"iteration":999,"passed_time":8.814184177,"remaining_time":0}
]}